{"objects":[{"itemIndex":6,"x":160.5,"y":10.7055464,"z":103.5,"rx":0.0,"ry":11.0,"rz":0.0},{"itemIndex":6,"x":154.5,"y":9.905796,"z":102.0,"rx":0.0,"ry":195.0,"rz":0.0},{"itemIndex":6,"x":156.0,"y":10.2609224,"z":102.0,"rx":0.0,"ry":259.0,"rz":0.0},{"itemIndex":6,"x":159.0,"y":10.5626678,"z":102.0,"rx":0.0,"ry":350.0,"rz":0.0},{"itemIndex":6,"x":168.0,"y":9.653275,"z":102.0,"rx":0.0,"ry":178.0,"rz":0.0},{"itemIndex":6,"x":156.0,"y":10.0604448,"z":100.5,"rx":0.0,"ry":25.9999981,"rz":0.0},{"itemIndex":6,"x":157.5,"y":10.3285971,"z":100.5,"rx":0.0,"ry":57.0,"rz":0.0},{"itemIndex":6,"x":159.0,"y":10.4923306,"z":100.5,"rx":0.0,"ry":204.0,"rz":0.0},{"itemIndex":6,"x":160.5,"y":10.3974991,"z":100.5,"rx":0.0,"ry":219.0,"rz":0.0},{"itemIndex":6,"x":163.5,"y":9.905425,"z":100.5,"rx":0.0,"ry":43.9999962,"rz":0.0},{"itemIndex":6,"x":165.0,"y":9.799436,"z":100.5,"rx":0.0,"ry":301.0,"rz":0.0},{"itemIndex":6,"x":150.0,"y":7.651607,"z":99.0,"rx":0.0,"ry":188.0,"rz":0.0},{"itemIndex":6,"x":157.5,"y":10.4209671,"z":99.0,"rx":0.0,"ry":114.0,"rz":0.0},{"itemIndex":6,"x":162.0,"y":10.3007517,"z":99.0,"rx":0.0,"ry":105.0,"rz":0.0},{"itemIndex":6,"x":163.5,"y":9.967043,"z":99.0,"rx":0.0,"ry":192.0,"rz":0.0},{"itemIndex":6,"x":168.0,"y":10.1190634,"z":99.0,"rx":0.0,"ry":233.0,"rz":0.0},{"itemIndex":6,"x":169.5,"y":10.2608881,"z":99.0,"rx":0.0,"ry":31.0000019,"rz":0.0},{"itemIndex":6,"x":151.5,"y":8.607624,"z":97.5,"rx":0.0,"ry":230.0,"rz":0.0},{"itemIndex":6,"x":154.5,"y":9.605804,"z":97.5,"rx":0.0,"ry":239.0,"rz":0.0},{"itemIndex":6,"x":163.5,"y":10.3828983,"z":97.5,"rx":0.0,"ry":104.0,"rz":0.0},{"itemIndex":6,"x":166.5,"y":10.2609224,"z":97.5,"rx":0.0,"ry":160.0,"rz":0.0},{"itemIndex":6,"x":168.0,"y":10.3577394,"z":97.5,"rx":0.0,"ry":315.0,"rz":0.0},{"itemIndex":6,"x":171.0,"y":10.3498354,"z":97.5,"rx":0.0,"ry":325.0,"rz":0.0},{"itemIndex":6,"x":150.0,"y":8.085147,"z":96.0,"rx":0.0,"ry":221.0,"rz":0.0},{"itemIndex":6,"x":159.0,"y":10.3721943,"z":96.0,"rx":0.0,"ry":174.0,"rz":0.0},{"itemIndex":6,"x":165.0,"y":10.709815,"z":96.0,"rx":0.0,"ry":104.0,"rz":0.0},{"itemIndex":6,"x":168.0,"y":10.7470064,"z":96.0,"rx":0.0,"ry":145.0,"rz":0.0},{"itemIndex":6,"x":148.5,"y":7.564616,"z":94.5,"rx":0.0,"ry":251.0,"rz":0.0},{"itemIndex":6,"x":156.0,"y":10.0185137,"z":94.5,"rx":0.0,"ry":279.0,"rz":0.0},{"itemIndex":6,"x":160.5,"y":10.6775541,"z":94.5,"rx":0.0,"ry":160.0,"rz":0.0},{"itemIndex":6,"x":162.0,"y":10.925293,"z":94.5,"rx":0.0,"ry":83.0,"rz":0.0},{"itemIndex":6,"x":163.5,"y":11.0742388,"z":94.5,"rx":0.0,"ry":119.0,"rz":0.0},{"itemIndex":6,"x":165.0,"y":10.8395891,"z":94.5,"rx":0.0,"ry":115.000008,"rz":0.0},{"itemIndex":6,"x":171.0,"y":10.3293333,"z":94.5,"rx":0.0,"ry":337.0,"rz":0.0},{"itemIndex":6,"x":148.5,"y":7.551876,"z":93.0,"rx":0.0,"ry":341.0,"rz":0.0},{"itemIndex":6,"x":151.5,"y":8.473659,"z":93.0,"rx":0.0,"ry":181.0,"rz":0.0},{"itemIndex":6,"x":153.0,"y":8.979428,"z":93.0,"rx":0.0,"ry":282.0,"rz":0.0},{"itemIndex":6,"x":162.0,"y":10.8479214,"z":93.0,"rx":0.0,"ry":164.0,"rz":0.0},{"itemIndex":6,"x":165.0,"y":11.0143223,"z":93.0,"rx":0.0,"ry":287.0,"rz":0.0},{"itemIndex":6,"x":168.0,"y":10.7945366,"z":93.0,"rx":0.0,"ry":189.0,"rz":0.0},{"itemIndex":6,"x":160.5,"y":10.6477528,"z":91.5,"rx":0.0,"ry":153.0,"rz":0.0},{"itemIndex":6,"x":163.5,"y":10.9850273,"z":91.5,"rx":0.0,"ry":265.0,"rz":0.0},{"itemIndex":6,"x":165.0,"y":10.7027254,"z":91.5,"rx":0.0,"ry":293.0,"rz":0.0},{"itemIndex":6,"x":166.5,"y":10.7136669,"z":91.5,"rx":0.0,"ry":203.0,"rz":0.0},{"itemIndex":6,"x":169.5,"y":10.7705011,"z":91.5,"rx":0.0,"ry":71.99999,"rz":0.0},{"itemIndex":6,"x":148.5,"y":7.71999645,"z":90.0,"rx":0.0,"ry":233.0,"rz":0.0},{"itemIndex":6,"x":156.0,"y":9.829322,"z":90.0,"rx":0.0,"ry":18.9999962,"rz":0.0},{"itemIndex":6,"x":160.5,"y":10.4915447,"z":90.0,"rx":0.0,"ry":63.0,"rz":0.0},{"itemIndex":6,"x":168.0,"y":10.4730692,"z":90.0,"rx":0.0,"ry":263.0,"rz":0.0},{"itemIndex":6,"x":171.0,"y":10.7299662,"z":90.0,"rx":0.0,"ry":59.0,"rz":0.0},{"itemIndex":1,"x":136.5,"y":-0.158157349,"z":88.5,"rx":0.0,"ry":0.0,"rz":0.0},{"itemIndex":6,"x":150.0,"y":8.255526,"z":88.5,"rx":0.0,"ry":170.0,"rz":0.0},{"itemIndex":6,"x":151.5,"y":8.540175,"z":88.5,"rx":0.0,"ry":68.0,"rz":0.0},{"itemIndex":6,"x":153.0,"y":9.042787,"z":88.5,"rx":0.0,"ry":107.0,"rz":0.0},{"itemIndex":6,"x":166.5,"y":10.5590982,"z":88.5,"rx":0.0,"ry":344.0,"rz":0.0},{"itemIndex":6,"x":171.0,"y":10.7355623,"z":88.5,"rx":0.0,"ry":120.000008,"rz":0.0},{"itemIndex":6,"x":159.0,"y":10.1544609,"z":87.0,"rx":0.0,"ry":14.000001,"rz":0.0},{"itemIndex":6,"x":162.0,"y":10.3012218,"z":87.0,"rx":0.0,"ry":25.0,"rz":0.0},{"itemIndex":6,"x":157.5,"y":9.979626,"z":85.5,"rx":0.0,"ry":150.0,"rz":0.0},{"itemIndex":6,"x":160.5,"y":10.2132215,"z":85.5,"rx":0.0,"ry":32.0,"rz":0.0},{"itemIndex":6,"x":168.0,"y":10.6442614,"z":85.5,"rx":0.0,"ry":163.0,"rz":0.0},{"itemIndex":6,"x":157.5,"y":9.888387,"z":84.0,"rx":0.0,"ry":164.0,"rz":0.0},{"itemIndex":6,"x":165.0,"y":10.6221008,"z":84.0,"rx":0.0,"ry":269.0,"rz":0.0},{"itemIndex":6,"x":169.5,"y":10.4975615,"z":84.0,"rx":0.0,"ry":180.0,"rz":0.0},{"itemIndex":6,"x":153.0,"y":8.153847,"z":82.5,"rx":0.0,"ry":91.00001,"rz":0.0},{"itemIndex":6,"x":154.5,"y":8.531221,"z":82.5,"rx":0.0,"ry":138.0,"rz":0.0},{"itemIndex":6,"x":163.5,"y":10.6367044,"z":82.5,"rx":0.0,"ry":309.0,"rz":0.0},{"itemIndex":6,"x":166.5,"y":10.8665171,"z":82.5,"rx":0.0,"ry":162.0,"rz":0.0},{"itemIndex":6,"x":151.5,"y":7.537542,"z":81.0,"rx":0.0,"ry":90.0,"rz":0.0},{"itemIndex":6,"x":153.0,"y":7.784203,"z":81.0,"rx":0.0,"ry":18.0000019,"rz":0.0},{"itemIndex":6,"x":162.0,"y":10.2823591,"z":81.0,"rx":0.0,"ry":187.0,"rz":0.0},{"itemIndex":6,"x":163.5,"y":10.7659321,"z":81.0,"rx":0.0,"ry":116.0,"rz":0.0},{"itemIndex":6,"x":166.5,"y":11.0658894,"z":81.0,"rx":0.0,"ry":338.0,"rz":0.0},{"itemIndex":6,"x":168.0,"y":10.9824657,"z":81.0,"rx":0.0,"ry":138.0,"rz":0.0},{"itemIndex":6,"x":153.0,"y":7.50795746,"z":79.5,"rx":0.0,"ry":322.0,"rz":0.0},{"itemIndex":6,"x":154.5,"y":8.040292,"z":79.5,"rx":0.0,"ry":256.0,"rz":0.0},{"itemIndex":6,"x":159.0,"y":9.484209,"z":79.5,"rx":0.0,"ry":104.0,"rz":0.0},{"itemIndex":6,"x":162.0,"y":10.2178831,"z":79.5,"rx":0.0,"ry":317.0,"rz":0.0},{"itemIndex":6,"x":166.5,"y":11.097455,"z":79.5,"rx":0.0,"ry":36.0,"rz":0.0},{"itemIndex":6,"x":168.0,"y":11.30039,"z":79.5,"rx":0.0,"ry":159.0,"rz":0.0},{"itemIndex":6,"x":169.5,"y":11.3009872,"z":79.5,"rx":0.0,"ry":280.0,"rz":0.0},{"itemIndex":6,"x":168.0,"y":11.2615929,"z":78.0,"rx":0.0,"ry":50.0000038,"rz":0.0},{"itemIndex":6,"x":169.5,"y":11.50339,"z":78.0,"rx":0.0,"ry":180.0,"rz":0.0},{"itemIndex":6,"x":171.0,"y":11.7266884,"z":78.0,"rx":0.0,"ry":181.0,"rz":0.0},{"itemIndex":6,"x":148.5,"y":7.48118925,"z":76.5,"rx":0.0,"ry":342.0,"rz":0.0},{"itemIndex":6,"x":150.0,"y":7.8100543,"z":76.5,"rx":0.0,"ry":181.0,"rz":0.0},{"itemIndex":6,"x":151.5,"y":8.09125,"z":76.5,"rx":0.0,"ry":113.0,"rz":0.0},{"itemIndex":6,"x":154.5,"y":8.522877,"z":76.5,"rx":0.0,"ry":99.99999,"rz":0.0},{"itemIndex":6,"x":162.0,"y":10.5326881,"z":76.5,"rx":0.0,"ry":290.0,"rz":0.0},{"itemIndex":6,"x":169.5,"y":11.5604134,"z":76.5,"rx":0.0,"ry":271.0,"rz":0.0},{"itemIndex":6,"x":171.0,"y":11.9229479,"z":76.5,"rx":0.0,"ry":227.0,"rz":0.0},{"itemIndex":6,"x":153.0,"y":8.632855,"z":75.0,"rx":0.0,"ry":328.0,"rz":0.0},{"itemIndex":6,"x":154.5,"y":8.765874,"z":75.0,"rx":0.0,"ry":266.0,"rz":0.0},{"itemIndex":6,"x":169.5,"y":11.7593794,"z":75.0,"rx":0.0,"ry":323.0,"rz":0.0},{"itemIndex":6,"x":171.0,"y":12.19852,"z":75.0,"rx":0.0,"ry":135.0,"rz":0.0},{"itemIndex":6,"x":142.5,"y":7.310022,"z":73.5,"rx":0.0,"ry":121.0,"rz":0.0},{"itemIndex":6,"x":153.0,"y":8.865486,"z":73.5,"rx":0.0,"ry":153.0,"rz":0.0},{"itemIndex":6,"x":156.0,"y":9.626627,"z":73.5,"rx":0.0,"ry":71.99999,"rz":0.0},{"itemIndex":6,"x":159.0,"y":10.8149252,"z":73.5,"rx":0.0,"ry":120.000008,"rz":0.0},{"itemIndex":6,"x":165.0,"y":11.61396,"z":73.5,"rx":0.0,"ry":38.0,"rz":0.0},{"itemIndex":6,"x":171.0,"y":12.40114,"z":73.5,"rx":0.0,"ry":165.0,"rz":0.0},{"itemIndex":6,"x":141.0,"y":7.044753,"z":72.0,"rx":0.0,"ry":155.0,"rz":0.0},{"itemIndex":6,"x":142.5,"y":7.690163,"z":72.0,"rx":0.0,"ry":308.0,"rz":0.0},{"itemIndex":6,"x":144.0,"y":8.275444,"z":72.0,"rx":0.0,"ry":303.0,"rz":0.0},{"itemIndex":6,"x":160.5,"y":11.5408983,"z":72.0,"rx":0.0,"ry":245.0,"rz":0.0},{"itemIndex":6,"x":166.5,"y":12.0306025,"z":72.0,"rx":0.0,"ry":336.0,"rz":0.0},{"itemIndex":6,"x":139.5,"y":7.20127773,"z":70.5,"rx":0.0,"ry":57.0,"rz":0.0},{"itemIndex":6,"x":141.0,"y":7.523837,"z":70.5,"rx":0.0,"ry":140.0,"rz":0.0},{"itemIndex":6,"x":153.0,"y":9.601114,"z":70.5,"rx":0.0,"ry":246.0,"rz":0.0},{"itemIndex":6,"x":156.0,"y":10.2712812,"z":70.5,"rx":0.0,"ry":91.00001,"rz":0.0},{"itemIndex":6,"x":162.0,"y":12.3334169,"z":70.5,"rx":0.0,"ry":306.0,"rz":0.0},{"itemIndex":6,"x":163.5,"y":12.53635,"z":70.5,"rx":0.0,"ry":38.0,"rz":0.0},{"itemIndex":6,"x":165.0,"y":12.4766912,"z":70.5,"rx":0.0,"ry":57.0,"rz":0.0},{"itemIndex":6,"x":169.5,"y":12.9571037,"z":70.5,"rx":0.0,"ry":180.0,"rz":0.0},{"itemIndex":6,"x":171.0,"y":13.2894688,"z":70.5,"rx":0.0,"ry":25.9999981,"rz":0.0},{"itemIndex":6,"x":139.5,"y":7.544516,"z":69.0,"rx":0.0,"ry":153.0,"rz":0.0},{"itemIndex":6,"x":142.5,"y":8.087415,"z":69.0,"rx":0.0,"ry":343.0,"rz":0.0},{"itemIndex":6,"x":144.0,"y":8.220529,"z":69.0,"rx":0.0,"ry":240.0,"rz":0.0},{"itemIndex":6,"x":148.5,"y":9.478102,"z":69.0,"rx":0.0,"ry":338.0,"rz":0.0},{"itemIndex":6,"x":157.5,"y":11.03915,"z":69.0,"rx":0.0,"ry":331.0,"rz":0.0},{"itemIndex":6,"x":159.0,"y":11.6599054,"z":69.0,"rx":0.0,"ry":109.0,"rz":0.0},{"itemIndex":6,"x":136.5,"y":7.07433844,"z":67.5,"rx":0.0,"ry":346.0,"rz":0.0},{"itemIndex":6,"x":142.5,"y":8.442496,"z":67.5,"rx":0.0,"ry":106.0,"rz":0.0},{"itemIndex":6,"x":145.5,"y":9.016212,"z":67.5,"rx":0.0,"ry":171.0,"rz":0.0},{"itemIndex":6,"x":151.5,"y":10.1741123,"z":67.5,"rx":0.0,"ry":159.0,"rz":0.0},{"itemIndex":6,"x":159.0,"y":11.8153648,"z":67.5,"rx":0.0,"ry":187.0,"rz":0.0},{"itemIndex":6,"x":168.0,"y":13.8096848,"z":67.5,"rx":0.0,"ry":329.0,"rz":0.0},{"itemIndex":6,"x":120.0,"y":7.22633076,"z":66.0,"rx":0.0,"ry":136.0,"rz":0.0},{"itemIndex":6,"x":127.5,"y":7.217162,"z":66.0,"rx":0.0,"ry":353.0,"rz":0.0},{"itemIndex":6,"x":138.0,"y":7.80624771,"z":66.0,"rx":0.0,"ry":123.999992,"rz":0.0},{"itemIndex":6,"x":139.5,"y":8.146853,"z":66.0,"rx":0.0,"ry":342.0,"rz":0.0},{"itemIndex":6,"x":142.5,"y":8.930722,"z":66.0,"rx":0.0,"ry":2.0,"rz":0.0},{"itemIndex":6,"x":147.0,"y":9.88077,"z":66.0,"rx":0.0,"ry":266.0,"rz":0.0},{"itemIndex":6,"x":151.5,"y":10.7798147,"z":66.0,"rx":0.0,"ry":356.0,"rz":0.0},{"itemIndex":6,"x":153.0,"y":11.12639,"z":66.0,"rx":0.0,"ry":240.0,"rz":0.0},{"itemIndex":6,"x":154.5,"y":11.2667866,"z":66.0,"rx":0.0,"ry":186.0,"rz":0.0},{"itemIndex":6,"x":159.0,"y":12.1143208,"z":66.0,"rx":0.0,"ry":182.0,"rz":0.0},{"itemIndex":6,"x":165.0,"y":13.9128923,"z":66.0,"rx":0.0,"ry":235.0,"rz":0.0},{"itemIndex":6,"x":123.0,"y":7.59024143,"z":64.5,"rx":0.0,"ry":133.0,"rz":0.0},{"itemIndex":6,"x":138.0,"y":8.404375,"z":64.5,"rx":0.0,"ry":5.0,"rz":0.0},{"itemIndex":6,"x":142.5,"y":9.504163,"z":64.5,"rx":0.0,"ry":161.0,"rz":0.0},{"itemIndex":6,"x":144.0,"y":9.737442,"z":64.5,"rx":0.0,"ry":143.0,"rz":0.0},{"itemIndex":6,"x":151.5,"y":11.1910515,"z":64.5,"rx":0.0,"ry":300.0,"rz":0.0},{"itemIndex":6,"x":154.5,"y":11.8802633,"z":64.5,"rx":0.0,"ry":357.0,"rz":0.0},{"itemIndex":6,"x":159.0,"y":12.5871973,"z":64.5,"rx":0.0,"ry":300.0,"rz":0.0},{"itemIndex":6,"x":169.5,"y":14.6257267,"z":64.5,"rx":0.0,"ry":191.0,"rz":0.0},{"itemIndex":6,"x":171.0,"y":14.9449425,"z":64.5,"rx":0.0,"ry":279.0,"rz":0.0},{"itemIndex":6,"x":112.5,"y":8.328116,"z":63.0,"rx":0.0,"ry":257.0,"rz":0.0},{"itemIndex":6,"x":115.5,"y":8.229556,"z":63.0,"rx":0.0,"ry":256.0,"rz":0.0},{"itemIndex":6,"x":126.0,"y":8.598762,"z":63.0,"rx":0.0,"ry":249.0,"rz":0.0},{"itemIndex":6,"x":138.0,"y":9.011384,"z":63.0,"rx":0.0,"ry":307.0,"rz":0.0},{"itemIndex":6,"x":145.5,"y":10.9400005,"z":63.0,"rx":0.0,"ry":94.99999,"rz":0.0},{"itemIndex":6,"x":147.0,"y":11.0421648,"z":63.0,"rx":0.0,"ry":353.0,"rz":0.0},{"itemIndex":6,"x":151.5,"y":11.8060818,"z":63.0,"rx":0.0,"ry":260.0,"rz":0.0},{"itemIndex":6,"x":153.0,"y":12.195755,"z":63.0,"rx":0.0,"ry":237.0,"rz":0.0},{"itemIndex":6,"x":157.5,"y":12.5721579,"z":63.0,"rx":0.0,"ry":310.0,"rz":0.0},{"itemIndex":6,"x":160.5,"y":13.2407446,"z":63.0,"rx":0.0,"ry":174.0,"rz":0.0},{"itemIndex":6,"x":163.5,"y":13.6245117,"z":63.0,"rx":0.0,"ry":258.0,"rz":0.0},{"itemIndex":6,"x":106.5,"y":7.463314,"z":61.5,"rx":0.0,"ry":25.0,"rz":0.0},{"itemIndex":6,"x":111.0,"y":8.645588,"z":61.5,"rx":0.0,"ry":184.0,"rz":0.0},{"itemIndex":6,"x":115.5,"y":8.41979,"z":61.5,"rx":0.0,"ry":148.0,"rz":0.0},{"itemIndex":6,"x":120.0,"y":8.055336,"z":61.5,"rx":0.0,"ry":304.0,"rz":0.0},{"itemIndex":6,"x":124.5,"y":8.915862,"z":61.5,"rx":0.0,"ry":108.0,"rz":0.0},{"itemIndex":6,"x":130.5,"y":8.636936,"z":61.5,"rx":0.0,"ry":42.0,"rz":0.0},{"itemIndex":6,"x":136.5,"y":8.838265,"z":61.5,"rx":0.0,"ry":311.0,"rz":0.0},{"itemIndex":6,"x":138.0,"y":9.347429,"z":61.5,"rx":0.0,"ry":167.0,"rz":0.0},{"itemIndex":6,"x":139.5,"y":10.0942574,"z":61.5,"rx":0.0,"ry":222.0,"rz":0.0},{"itemIndex":6,"x":145.5,"y":11.4280424,"z":61.5,"rx":0.0,"ry":177.0,"rz":0.0},{"itemIndex":6,"x":147.0,"y":11.5586643,"z":61.5,"rx":0.0,"ry":164.0,"rz":0.0},{"itemIndex":6,"x":156.0,"y":13.2346869,"z":61.5,"rx":0.0,"ry":245.0,"rz":0.0},{"itemIndex":6,"x":165.0,"y":14.0430956,"z":61.5,"rx":0.0,"ry":271.0,"rz":0.0},{"itemIndex":6,"x":105.0,"y":7.209077,"z":59.9999962,"rx":0.0,"ry":310.0,"rz":0.0},{"itemIndex":6,"x":109.5,"y":9.186885,"z":59.9999962,"rx":0.0,"ry":357.0,"rz":0.0},{"itemIndex":6,"x":111.0,"y":9.331415,"z":59.9999962,"rx":0.0,"ry":68.0,"rz":0.0},{"itemIndex":6,"x":123.0,"y":9.077814,"z":59.9999962,"rx":0.0,"ry":357.0,"rz":0.0},{"itemIndex":6,"x":132.0,"y":8.727743,"z":59.9999962,"rx":0.0,"ry":59.0,"rz":0.0},{"itemIndex":6,"x":135.0,"y":9.049936,"z":59.9999962,"rx":0.0,"ry":133.0,"rz":0.0},{"itemIndex":6,"x":147.0,"y":11.93113,"z":59.9999962,"rx":0.0,"ry":17.0,"rz":0.0},{"itemIndex":6,"x":148.5,"y":12.2039261,"z":59.9999962,"rx":0.0,"ry":29.0,"rz":0.0},{"itemIndex":6,"x":154.5,"y":13.5439482,"z":59.9999962,"rx":0.0,"ry":52.0,"rz":0.0},{"itemIndex":6,"x":163.5,"y":14.0269566,"z":59.9999962,"rx":0.0,"ry":25.9999981,"rz":0.0},{"itemIndex":6,"x":166.5,"y":14.8785477,"z":59.9999962,"rx":0.0,"ry":24.0,"rz":0.0},{"itemIndex":6,"x":168.0,"y":15.1451912,"z":59.9999962,"rx":0.0,"ry":238.0,"rz":0.0},{"itemIndex":6,"x":105.0,"y":7.72898,"z":58.5,"rx":0.0,"ry":287.0,"rz":0.0},{"itemIndex":6,"x":115.5,"y":9.134875,"z":58.5,"rx":0.0,"ry":230.0,"rz":0.0},{"itemIndex":6,"x":126.0,"y":9.198609,"z":58.5,"rx":0.0,"ry":185.0,"rz":0.0},{"itemIndex":6,"x":135.0,"y":9.067339,"z":58.5,"rx":0.0,"ry":332.0,"rz":0.0},{"itemIndex":6,"x":136.5,"y":9.420404,"z":58.5,"rx":0.0,"ry":250.0,"rz":0.0},{"itemIndex":6,"x":147.0,"y":11.9330215,"z":58.5,"rx":0.0,"ry":227.0,"rz":0.0},{"itemIndex":6,"x":150.0,"y":12.871027,"z":58.5,"rx":0.0,"ry":41.0,"rz":0.0},{"itemIndex":6,"x":151.5,"y":13.4003172,"z":58.5,"rx":0.0,"ry":70.0,"rz":0.0},{"itemIndex":6,"x":160.5,"y":13.6324129,"z":58.5,"rx":0.0,"ry":286.0,"rz":0.0},{"itemIndex":6,"x":166.5,"y":15.0536366,"z":58.5,"rx":0.0,"ry":123.0,"rz":0.0},{"itemIndex":6,"x":171.0,"y":15.8346682,"z":58.5,"rx":0.0,"ry":268.0,"rz":0.0},{"itemIndex":6,"x":106.5,"y":8.910367,"z":57.0,"rx":0.0,"ry":277.0,"rz":0.0},{"itemIndex":6,"x":111.0,"y":10.01101,"z":57.0,"rx":0.0,"ry":5.0,"rz":0.0},{"itemIndex":0,"x":112.5,"y":9.773254,"z":57.0,"rx":0.0,"ry":0.0,"rz":0.0},{"itemIndex":6,"x":115.5,"y":9.200621,"z":57.0,"rx":0.0,"ry":194.0,"rz":0.0},{"itemIndex":6,"x":123.0,"y":9.613128,"z":57.0,"rx":0.0,"ry":244.0,"rz":0.0},{"itemIndex":6,"x":124.5,"y":9.385638,"z":57.0,"rx":0.0,"ry":23.0,"rz":0.0},{"itemIndex":6,"x":127.5,"y":8.761344,"z":57.0,"rx":0.0,"ry":324.0,"rz":0.0},{"itemIndex":6,"x":133.5,"y":8.69001,"z":57.0,"rx":0.0,"ry":296.0,"rz":0.0},{"itemIndex":6,"x":141.0,"y":11.03793,"z":57.0,"rx":0.0,"ry":102.0,"rz":0.0},{"itemIndex":6,"x":150.0,"y":13.1630449,"z":57.0,"rx":0.0,"ry":185.0,"rz":0.0},{"itemIndex":6,"x":159.0,"y":14.2617292,"z":57.0,"rx":0.0,"ry":337.0,"rz":0.0},{"itemIndex":6,"x":160.5,"y":14.1335163,"z":57.0,"rx":0.0,"ry":212.0,"rz":0.0},{"itemIndex":6,"x":162.0,"y":14.2001295,"z":57.0,"rx":0.0,"ry":37.0,"rz":0.0},{"itemIndex":6,"x":103.5,"y":8.283395,"z":55.5,"rx":0.0,"ry":185.0,"rz":0.0},{"itemIndex":6,"x":118.5,"y":9.738763,"z":55.5,"rx":0.0,"ry":123.999992,"rz":0.0},{"itemIndex":6,"x":120.0,"y":9.520881,"z":55.5,"rx":0.0,"ry":88.0,"rz":0.0},{"itemIndex":6,"x":121.5,"y":9.4298315,"z":55.5,"rx":0.0,"ry":155.0,"rz":0.0},{"itemIndex":6,"x":123.0,"y":9.352762,"z":55.5,"rx":0.0,"ry":158.0,"rz":0.0},{"itemIndex":6,"x":124.5,"y":9.190345,"z":55.5,"rx":0.0,"ry":233.0,"rz":0.0},{"itemIndex":6,"x":126.0,"y":8.842901,"z":55.5,"rx":0.0,"ry":171.0,"rz":0.0},{"itemIndex":6,"x":130.5,"y":8.631985,"z":55.5,"rx":0.0,"ry":325.0,"rz":0.0},{"itemIndex":6,"x":132.0,"y":8.599424,"z":55.5,"rx":0.0,"ry":213.0,"rz":0.0},{"itemIndex":6,"x":135.0,"y":8.894778,"z":55.5,"rx":0.0,"ry":309.0,"rz":0.0},{"itemIndex":6,"x":136.5,"y":9.329161,"z":55.5,"rx":0.0,"ry":201.0,"rz":0.0},{"itemIndex":6,"x":142.5,"y":11.33419,"z":55.5,"rx":0.0,"ry":333.0,"rz":0.0},{"itemIndex":6,"x":144.0,"y":11.5162935,"z":55.5,"rx":0.0,"ry":34.0,"rz":0.0},{"itemIndex":6,"x":145.5,"y":11.8417454,"z":55.5,"rx":0.0,"ry":326.0,"rz":0.0},{"itemIndex":6,"x":156.0,"y":14.2872448,"z":55.5,"rx":0.0,"ry":311.0,"rz":0.0},{"itemIndex":6,"x":157.5,"y":14.3590994,"z":55.5,"rx":0.0,"ry":301.0,"rz":0.0},{"itemIndex":6,"x":159.0,"y":14.3797436,"z":55.5,"rx":0.0,"ry":155.0,"rz":0.0},{"itemIndex":6,"x":168.0,"y":15.377573,"z":55.5,"rx":0.0,"ry":292.0,"rz":0.0},{"itemIndex":6,"x":103.5,"y":8.565261,"z":54.0,"rx":0.0,"ry":300.0,"rz":0.0},{"itemIndex":6,"x":105.0,"y":8.990187,"z":54.0,"rx":0.0,"ry":77.0,"rz":0.0},{"itemIndex":6,"x":111.0,"y":10.1006222,"z":54.0,"rx":0.0,"ry":345.0,"rz":0.0},{"itemIndex":6,"x":112.5,"y":10.1424351,"z":54.0,"rx":0.0,"ry":209.0,"rz":0.0},{"itemIndex":6,"x":115.5,"y":10.21403,"z":54.0,"rx":0.0,"ry":155.0,"rz":0.0},{"itemIndex":6,"x":118.5,"y":9.846996,"z":54.0,"rx":0.0,"ry":322.0,"rz":0.0},{"itemIndex":6,"x":121.5,"y":9.576336,"z":54.0,"rx":0.0,"ry":335.0,"rz":0.0},{"itemIndex":6,"x":124.5,"y":9.191376,"z":54.0,"rx":0.0,"ry":172.0,"rz":0.0},{"itemIndex":6,"x":126.0,"y":8.756656,"z":54.0,"rx":0.0,"ry":108.0,"rz":0.0},{"itemIndex":6,"x":129.0,"y":8.29266548,"z":54.0,"rx":0.0,"ry":225.0,"rz":0.0},{"itemIndex":6,"x":130.5,"y":8.441739,"z":54.0,"rx":0.0,"ry":306.0,"rz":0.0},{"itemIndex":6,"x":132.0,"y":8.369962,"z":54.0,"rx":0.0,"ry":276.0,"rz":0.0},{"itemIndex":6,"x":133.5,"y":8.382671,"z":54.0,"rx":0.0,"ry":340.0,"rz":0.0},{"itemIndex":6,"x":136.5,"y":9.523297,"z":54.0,"rx":0.0,"ry":149.0,"rz":0.0},{"itemIndex":6,"x":139.5,"y":10.71154,"z":54.0,"rx":0.0,"ry":97.0,"rz":0.0},{"itemIndex":6,"x":142.5,"y":11.3684282,"z":54.0,"rx":0.0,"ry":195.0,"rz":0.0},{"itemIndex":6,"x":144.0,"y":11.5045166,"z":54.0,"rx":0.0,"ry":262.0,"rz":0.0},{"itemIndex":6,"x":166.5,"y":15.620348,"z":54.0,"rx":0.0,"ry":306.0,"rz":0.0},{"itemIndex":6,"x":171.0,"y":16.0628548,"z":54.0,"rx":0.0,"ry":37.0,"rz":0.0},{"itemIndex":6,"x":103.5,"y":9.154788,"z":52.5,"rx":0.0,"ry":202.0,"rz":0.0},{"itemIndex":6,"x":108.0,"y":9.739358,"z":52.5,"rx":0.0,"ry":219.0,"rz":0.0},{"itemIndex":6,"x":114.0,"y":10.44721,"z":52.5,"rx":0.0,"ry":9.000001,"rz":0.0},{"itemIndex":6,"x":124.5,"y":9.042815,"z":52.5,"rx":0.0,"ry":116.999992,"rz":0.0},{"itemIndex":6,"x":127.5,"y":8.122179,"z":52.5,"rx":0.0,"ry":358.0,"rz":0.0},{"itemIndex":6,"x":132.0,"y":8.158255,"z":52.5,"rx":0.0,"ry":220.0,"rz":0.0},{"itemIndex":6,"x":135.0,"y":8.558109,"z":52.5,"rx":0.0,"ry":102.0,"rz":0.0},{"itemIndex":6,"x":141.0,"y":10.8479013,"z":52.5,"rx":0.0,"ry":303.0,"rz":0.0},{"itemIndex":6,"x":142.5,"y":11.254693,"z":52.5,"rx":0.0,"ry":99.0,"rz":0.0},{"itemIndex":6,"x":150.0,"y":13.7122564,"z":52.5,"rx":0.0,"ry":218.0,"rz":0.0},{"itemIndex":6,"x":157.5,"y":14.5348606,"z":52.5,"rx":0.0,"ry":248.0,"rz":0.0},{"itemIndex":6,"x":159.0,"y":14.7062941,"z":52.5,"rx":0.0,"ry":135.0,"rz":0.0},{"itemIndex":6,"x":171.0,"y":16.2258625,"z":52.5,"rx":0.0,"ry":223.0,"rz":0.0},{"itemIndex":6,"x":103.5,"y":9.694659,"z":51.0,"rx":0.0,"ry":339.0,"rz":0.0},{"itemIndex":6,"x":121.5,"y":9.876856,"z":51.0,"rx":0.0,"ry":143.0,"rz":0.0},{"itemIndex":6,"x":124.5,"y":9.043251,"z":51.0,"rx":0.0,"ry":180.0,"rz":0.0},{"itemIndex":6,"x":130.5,"y":7.896976,"z":51.0,"rx":0.0,"ry":277.0,"rz":0.0},{"itemIndex":6,"x":135.0,"y":8.434244,"z":51.0,"rx":0.0,"ry":9.000001,"rz":0.0},{"itemIndex":6,"x":141.0,"y":10.7319031,"z":51.0,"rx":0.0,"ry":7.999999,"rz":0.0},{"itemIndex":6,"x":150.0,"y":13.8310127,"z":51.0,"rx":0.0,"ry":9.000001,"rz":0.0},{"itemIndex":6,"x":156.0,"y":14.5159435,"z":51.0,"rx":0.0,"ry":152.0,"rz":0.0},{"itemIndex":6,"x":159.0,"y":14.81551,"z":51.0,"rx":0.0,"ry":164.0,"rz":0.0},{"itemIndex":6,"x":163.5,"y":14.5561209,"z":51.0,"rx":0.0,"ry":97.0,"rz":0.0},{"itemIndex":6,"x":165.0,"y":14.9750824,"z":51.0,"rx":0.0,"ry":349.0,"rz":0.0},{"itemIndex":6,"x":166.5,"y":15.4808941,"z":51.0,"rx":0.0,"ry":265.0,"rz":0.0},{"itemIndex":6,"x":169.5,"y":15.9094057,"z":51.0,"rx":0.0,"ry":239.0,"rz":0.0},{"itemIndex":6,"x":106.5,"y":10.0365372,"z":49.5,"rx":0.0,"ry":131.0,"rz":0.0},{"itemIndex":6,"x":111.0,"y":10.8058844,"z":49.5,"rx":0.0,"ry":224.0,"rz":0.0},{"itemIndex":6,"x":142.5,"y":11.1087914,"z":49.5,"rx":0.0,"ry":280.0,"rz":0.0},{"itemIndex":6,"x":156.0,"y":14.6168547,"z":49.5,"rx":0.0,"ry":207.0,"rz":0.0},{"itemIndex":6,"x":157.5,"y":14.8155479,"z":49.5,"rx":0.0,"ry":210.0,"rz":0.0},{"itemIndex":6,"x":171.0,"y":15.72491,"z":49.5,"rx":0.0,"ry":122.000008,"rz":0.0},{"itemIndex":6,"x":103.5,"y":10.5820322,"z":48.0,"rx":0.0,"ry":109.0,"rz":0.0},{"itemIndex":6,"x":111.0,"y":10.5978308,"z":48.0,"rx":0.0,"ry":331.0,"rz":0.0},{"itemIndex":6,"x":112.5,"y":10.9165316,"z":48.0,"rx":0.0,"ry":56.0000038,"rz":0.0},{"itemIndex":6,"x":115.5,"y":11.1925344,"z":48.0,"rx":0.0,"ry":103.0,"rz":0.0},{"itemIndex":6,"x":117.0,"y":11.0460892,"z":48.0,"rx":0.0,"ry":306.0,"rz":0.0},{"itemIndex":6,"x":120.0,"y":10.3569441,"z":48.0,"rx":0.0,"ry":220.0,"rz":0.0},{"itemIndex":6,"x":123.0,"y":9.259914,"z":48.0,"rx":0.0,"ry":276.0,"rz":0.0},{"itemIndex":6,"x":133.5,"y":7.980975,"z":48.0,"rx":0.0,"ry":343.0,"rz":0.0},{"itemIndex":6,"x":138.0,"y":9.411029,"z":48.0,"rx":0.0,"ry":239.0,"rz":0.0},{"itemIndex":6,"x":139.5,"y":9.810119,"z":48.0,"rx":0.0,"ry":182.0,"rz":0.0},{"itemIndex":0,"x":142.5,"y":10.9942017,"z":48.0,"rx":0.0,"ry":0.0,"rz":0.0},{"itemIndex":6,"x":144.0,"y":11.5368109,"z":48.0,"rx":0.0,"ry":273.0,"rz":0.0},{"itemIndex":6,"x":150.0,"y":13.7040472,"z":48.0,"rx":0.0,"ry":165.0,"rz":0.0},{"itemIndex":6,"x":153.0,"y":13.9824018,"z":48.0,"rx":0.0,"ry":92.0,"rz":0.0},{"itemIndex":6,"x":156.0,"y":14.4606667,"z":48.0,"rx":0.0,"ry":108.0,"rz":0.0},{"itemIndex":6,"x":157.5,"y":14.5990992,"z":48.0,"rx":0.0,"ry":85.0,"rz":0.0},{"itemIndex":6,"x":171.0,"y":15.3946066,"z":48.0,"rx":0.0,"ry":86.99999,"rz":0.0},{"itemIndex":6,"x":103.5,"y":10.9017239,"z":46.5,"rx":0.0,"ry":189.0,"rz":0.0},{"itemIndex":6,"x":108.0,"y":10.2900763,"z":46.5,"rx":0.0,"ry":82.0,"rz":0.0},{"itemIndex":6,"x":114.0,"y":10.8154926,"z":46.5,"rx":0.0,"ry":315.0,"rz":0.0},{"itemIndex":6,"x":124.5,"y":8.893467,"z":46.5,"rx":0.0,"ry":97.0,"rz":0.0},{"itemIndex":6,"x":127.5,"y":8.4250145,"z":46.5,"rx":0.0,"ry":162.0,"rz":0.0},{"itemIndex":6,"x":129.0,"y":8.468677,"z":46.5,"rx":0.0,"ry":45.0000038,"rz":0.0},{"itemIndex":6,"x":130.5,"y":8.277637,"z":46.5,"rx":0.0,"ry":168.0,"rz":0.0},{"itemIndex":6,"x":138.0,"y":9.477873,"z":46.5,"rx":0.0,"ry":334.0,"rz":0.0},{"itemIndex":6,"x":141.0,"y":10.3254585,"z":46.5,"rx":0.0,"ry":71.99999,"rz":0.0},{"itemIndex":6,"x":147.0,"y":12.7198248,"z":46.5,"rx":0.0,"ry":155.0,"rz":0.0},{"itemIndex":6,"x":150.0,"y":13.4651241,"z":46.5,"rx":0.0,"ry":342.0,"rz":0.0},{"itemIndex":6,"x":157.5,"y":14.2848206,"z":46.5,"rx":0.0,"ry":199.0,"rz":0.0},{"itemIndex":6,"x":166.5,"y":14.5873461,"z":46.5,"rx":0.0,"ry":32.0,"rz":0.0},{"itemIndex":6,"x":168.0,"y":14.753231,"z":46.5,"rx":0.0,"ry":270.0,"rz":0.0},{"itemIndex":6,"x":169.5,"y":14.9076862,"z":46.5,"rx":0.0,"ry":237.0,"rz":0.0},{"itemIndex":6,"x":105.0,"y":10.9890394,"z":45.0,"rx":0.0,"ry":2.0,"rz":0.0},{"itemIndex":6,"x":118.5,"y":10.5931873,"z":45.0,"rx":0.0,"ry":212.0,"rz":0.0},{"itemIndex":6,"x":120.0,"y":10.2310133,"z":45.0,"rx":0.0,"ry":141.0,"rz":0.0},{"itemIndex":6,"x":121.5,"y":9.637219,"z":45.0,"rx":0.0,"ry":335.0,"rz":0.0},{"itemIndex":6,"x":123.0,"y":9.275423,"z":45.0,"rx":0.0,"ry":354.0,"rz":0.0},{"itemIndex":6,"x":124.5,"y":8.969367,"z":45.0,"rx":0.0,"ry":254.0,"rz":0.0},{"itemIndex":6,"x":126.0,"y":8.726564,"z":45.0,"rx":0.0,"ry":285.0,"rz":0.0},{"itemIndex":6,"x":127.5,"y":8.47997,"z":45.0,"rx":0.0,"ry":129.0,"rz":0.0},{"itemIndex":6,"x":129.0,"y":8.568491,"z":45.0,"rx":0.0,"ry":327.0,"rz":0.0},{"itemIndex":6,"x":130.5,"y":8.592362,"z":45.0,"rx":0.0,"ry":127.000008,"rz":0.0},{"itemIndex":6,"x":132.0,"y":8.483966,"z":45.0,"rx":0.0,"ry":137.0,"rz":0.0},{"itemIndex":6,"x":144.0,"y":11.0056362,"z":45.0,"rx":0.0,"ry":30.0000019,"rz":0.0},{"itemIndex":6,"x":159.0,"y":13.6885681,"z":45.0,"rx":0.0,"ry":234.0,"rz":0.0},{"itemIndex":6,"x":162.0,"y":13.5509319,"z":45.0,"rx":0.0,"ry":203.0,"rz":0.0},{"itemIndex":6,"x":169.5,"y":14.59973,"z":45.0,"rx":0.0,"ry":292.0,"rz":0.0},{"itemIndex":6,"x":108.0,"y":10.8272419,"z":43.5000038,"rx":0.0,"ry":321.0,"rz":0.0},{"itemIndex":6,"x":111.0,"y":10.479434,"z":43.5000038,"rx":0.0,"ry":232.0,"rz":0.0},{"itemIndex":6,"x":112.5,"y":10.7234259,"z":43.5000038,"rx":0.0,"ry":45.0000038,"rz":0.0},{"itemIndex":6,"x":117.0,"y":10.7953968,"z":43.5000038,"rx":0.0,"ry":142.0,"rz":0.0},{"itemIndex":6,"x":121.5,"y":9.952945,"z":43.5000038,"rx":0.0,"ry":223.0,"rz":0.0},{"itemIndex":6,"x":123.0,"y":9.360226,"z":43.5000038,"rx":0.0,"ry":123.0,"rz":0.0},{"itemIndex":6,"x":136.5,"y":9.057552,"z":43.5000038,"rx":0.0,"ry":338.0,"rz":0.0},{"itemIndex":6,"x":145.5,"y":11.2051811,"z":43.5000038,"rx":0.0,"ry":344.0,"rz":0.0},{"itemIndex":6,"x":148.5,"y":12.3210211,"z":43.5000038,"rx":0.0,"ry":92.0,"rz":0.0},{"itemIndex":6,"x":156.0,"y":13.4666548,"z":43.5000038,"rx":0.0,"ry":232.0,"rz":0.0},{"itemIndex":6,"x":157.5,"y":13.231142,"z":43.5000038,"rx":0.0,"ry":142.0,"rz":0.0},{"itemIndex":6,"x":165.0,"y":13.3988419,"z":43.5000038,"rx":0.0,"ry":76.0,"rz":0.0},{"itemIndex":6,"x":166.5,"y":13.6519384,"z":43.5000038,"rx":0.0,"ry":136.0,"rz":0.0},{"itemIndex":6,"x":106.5,"y":11.52561,"z":42.0,"rx":0.0,"ry":248.0,"rz":0.0},{"itemIndex":6,"x":112.5,"y":10.850831,"z":42.0,"rx":0.0,"ry":157.0,"rz":0.0},{"itemIndex":6,"x":114.0,"y":11.1243181,"z":42.0,"rx":0.0,"ry":17.0,"rz":0.0},{"itemIndex":6,"x":120.0,"y":10.53783,"z":42.0,"rx":0.0,"ry":218.0,"rz":0.0},{"itemIndex":6,"x":133.5,"y":8.744201,"z":42.0,"rx":0.0,"ry":276.0,"rz":0.0},{"itemIndex":6,"x":139.5,"y":9.455653,"z":42.0,"rx":0.0,"ry":223.0,"rz":0.0},{"itemIndex":6,"x":142.5,"y":10.0596018,"z":42.0,"rx":0.0,"ry":251.0,"rz":0.0},{"itemIndex":6,"x":150.0,"y":12.4500628,"z":42.0,"rx":0.0,"ry":340.0,"rz":0.0},{"itemIndex":6,"x":151.5,"y":12.8256445,"z":42.0,"rx":0.0,"ry":233.0,"rz":0.0},{"itemIndex":6,"x":157.5,"y":12.8491859,"z":42.0,"rx":0.0,"ry":290.0,"rz":0.0},{"itemIndex":6,"x":118.5,"y":10.5730457,"z":40.5,"rx":0.0,"ry":255.0,"rz":0.0},{"itemIndex":6,"x":120.0,"y":10.37621,"z":40.5,"rx":0.0,"ry":153.0,"rz":0.0},{"itemIndex":6,"x":121.5,"y":10.0052595,"z":40.5,"rx":0.0,"ry":155.0,"rz":0.0},{"itemIndex":6,"x":124.5,"y":9.636152,"z":40.5,"rx":0.0,"ry":170.0,"rz":0.0},{"itemIndex":6,"x":126.0,"y":9.62857151,"z":40.5,"rx":0.0,"ry":123.0,"rz":0.0},{"itemIndex":6,"x":135.0,"y":8.928946,"z":40.5,"rx":0.0,"ry":219.0,"rz":0.0},{"itemIndex":6,"x":139.5,"y":8.832619,"z":40.5,"rx":0.0,"ry":75.0,"rz":0.0},{"itemIndex":6,"x":144.0,"y":10.1200762,"z":40.5,"rx":0.0,"ry":66.0,"rz":0.0},{"itemIndex":6,"x":148.5,"y":11.3882523,"z":40.5,"rx":0.0,"ry":11.0,"rz":0.0},{"itemIndex":6,"x":160.5,"y":12.09278,"z":40.5,"rx":0.0,"ry":266.0,"rz":0.0},{"itemIndex":6,"x":165.0,"y":12.5301638,"z":40.5,"rx":0.0,"ry":212.0,"rz":0.0},{"itemIndex":6,"x":105.0,"y":12.5904427,"z":39.0,"rx":0.0,"ry":324.0,"rz":0.0},{"itemIndex":6,"x":111.0,"y":11.2804623,"z":39.0,"rx":0.0,"ry":310.0,"rz":0.0},{"itemIndex":6,"x":115.5,"y":10.7812576,"z":39.0,"rx":0.0,"ry":81.0,"rz":0.0},{"itemIndex":6,"x":120.0,"y":10.7168665,"z":39.0,"rx":0.0,"ry":319.0,"rz":0.0},{"itemIndex":6,"x":123.0,"y":9.91537,"z":39.0,"rx":0.0,"ry":25.0,"rz":0.0},{"itemIndex":6,"x":139.5,"y":8.619703,"z":39.0,"rx":0.0,"ry":2.0,"rz":0.0},{"itemIndex":6,"x":141.0,"y":8.829165,"z":39.0,"rx":0.0,"ry":163.0,"rz":0.0},{"itemIndex":6,"x":151.5,"y":12.0695553,"z":39.0,"rx":0.0,"ry":183.0,"rz":0.0},{"itemIndex":6,"x":157.5,"y":12.4478035,"z":39.0,"rx":0.0,"ry":125.0,"rz":0.0},{"itemIndex":0,"x":159.0,"y":12.1708679,"z":39.0,"rx":0.0,"ry":0.0,"rz":0.0},{"itemIndex":6,"x":163.5,"y":12.04897,"z":39.0,"rx":0.0,"ry":119.0,"rz":0.0},{"itemIndex":6,"x":169.5,"y":12.7034359,"z":39.0,"rx":0.0,"ry":147.0,"rz":0.0},{"itemIndex":6,"x":105.0,"y":12.7410765,"z":37.5,"rx":0.0,"ry":277.0,"rz":0.0},{"itemIndex":6,"x":108.0,"y":12.2487583,"z":37.5,"rx":0.0,"ry":28.0000019,"rz":0.0},{"itemIndex":6,"x":111.0,"y":11.553401,"z":37.5,"rx":0.0,"ry":61.9999962,"rz":0.0},{"itemIndex":6,"x":114.0,"y":11.0758171,"z":37.5,"rx":0.0,"ry":224.0,"rz":0.0},{"itemIndex":6,"x":115.5,"y":10.9590969,"z":37.5,"rx":0.0,"ry":91.00001,"rz":0.0},{"itemIndex":6,"x":117.0,"y":10.822669,"z":37.5,"rx":0.0,"ry":304.0,"rz":0.0},{"itemIndex":6,"x":120.0,"y":10.9656925,"z":37.5,"rx":0.0,"ry":249.0,"rz":0.0},{"itemIndex":6,"x":138.0,"y":8.745286,"z":37.5,"rx":0.0,"ry":335.0,"rz":0.0},{"itemIndex":6,"x":144.0,"y":9.92717552,"z":37.5,"rx":0.0,"ry":114.0,"rz":0.0},{"itemIndex":6,"x":148.5,"y":10.8517218,"z":37.5,"rx":0.0,"ry":22.0,"rz":0.0},{"itemIndex":6,"x":156.0,"y":12.2834167,"z":37.5,"rx":0.0,"ry":321.0,"rz":0.0},{"itemIndex":6,"x":157.5,"y":12.0505228,"z":37.5,"rx":0.0,"ry":301.0,"rz":0.0},{"itemIndex":6,"x":159.0,"y":11.6516323,"z":37.5,"rx":0.0,"ry":289.0,"rz":0.0},{"itemIndex":0,"x":166.5,"y":11.8505859,"z":37.5,"rx":0.0,"ry":0.0,"rz":0.0},{"itemIndex":6,"x":168.0,"y":12.1896486,"z":37.5,"rx":0.0,"ry":81.0,"rz":0.0},{"itemIndex":6,"x":171.0,"y":12.2546835,"z":37.5,"rx":0.0,"ry":103.0,"rz":0.0},{"itemIndex":6,"x":105.0,"y":13.2143316,"z":36.0,"rx":0.0,"ry":123.999992,"rz":0.0},{"itemIndex":6,"x":108.0,"y":12.3177032,"z":36.0,"rx":0.0,"ry":32.0,"rz":0.0},{"itemIndex":6,"x":109.5,"y":12.1139641,"z":36.0,"rx":0.0,"ry":303.0,"rz":0.0},{"itemIndex":6,"x":123.0,"y":10.66848,"z":36.0,"rx":0.0,"ry":99.0,"rz":0.0},{"itemIndex":6,"x":124.5,"y":10.4665709,"z":36.0,"rx":0.0,"ry":173.0,"rz":0.0},{"itemIndex":6,"x":136.5,"y":8.475462,"z":36.0,"rx":0.0,"ry":258.0,"rz":0.0},{"itemIndex":6,"x":144.0,"y":10.0685139,"z":36.0,"rx":0.0,"ry":269.0,"rz":0.0},{"itemIndex":6,"x":148.5,"y":10.9029341,"z":36.0,"rx":0.0,"ry":306.0,"rz":0.0},{"itemIndex":6,"x":151.5,"y":12.0301609,"z":36.0,"rx":0.0,"ry":165.0,"rz":0.0},{"itemIndex":6,"x":153.0,"y":12.1376019,"z":36.0,"rx":0.0,"ry":306.0,"rz":0.0},{"itemIndex":6,"x":156.0,"y":11.8712969,"z":36.0,"rx":0.0,"ry":219.0,"rz":0.0},{"itemIndex":6,"x":166.5,"y":11.45333,"z":36.0,"rx":0.0,"ry":334.0,"rz":0.0},{"itemIndex":6,"x":168.0,"y":11.5128145,"z":36.0,"rx":0.0,"ry":356.0,"rz":0.0},{"itemIndex":6,"x":169.5,"y":11.5788774,"z":36.0,"rx":0.0,"ry":259.0,"rz":0.0}]}