{"objects":[{"itemIndex":6,"x":-172.5,"y":4.903754,"z":34.5,"rx":0.0,"ry":182.0,"rz":0.0},{"itemIndex":6,"x":-168.0,"y":3.90752387,"z":34.5,"rx":0.0,"ry":161.0,"rz":0.0},{"itemIndex":6,"x":-165.0,"y":4.181458,"z":34.5,"rx":0.0,"ry":297.0,"rz":0.0},{"itemIndex":6,"x":-162.0,"y":4.6896615,"z":34.5,"rx":0.0,"ry":268.0,"rz":0.0},{"itemIndex":6,"x":-153.0,"y":4.072447,"z":34.5,"rx":0.0,"ry":329.0,"rz":0.0},{"itemIndex":6,"x":-151.5,"y":4.142119,"z":34.5,"rx":0.0,"ry":338.0,"rz":0.0},{"itemIndex":6,"x":-144.0,"y":5.345564,"z":34.5,"rx":0.0,"ry":141.0,"rz":0.0},{"itemIndex":6,"x":-141.0,"y":6.03710461,"z":34.5,"rx":0.0,"ry":272.0,"rz":0.0},{"itemIndex":6,"x":-136.5,"y":6.58711,"z":34.5,"rx":0.0,"ry":215.0,"rz":0.0},{"itemIndex":6,"x":-135.0,"y":6.872776,"z":34.5,"rx":0.0,"ry":2.0,"rz":0.0},{"itemIndex":6,"x":-130.5,"y":6.85526133,"z":34.5,"rx":0.0,"ry":9.000001,"rz":0.0},{"itemIndex":6,"x":-129.0,"y":7.053208,"z":34.5,"rx":0.0,"ry":119.0,"rz":0.0},{"itemIndex":6,"x":-121.5,"y":7.44674158,"z":34.5,"rx":0.0,"ry":11.0,"rz":0.0},{"itemIndex":6,"x":-105.0,"y":3.5669806,"z":34.5,"rx":0.0,"ry":137.0,"rz":0.0},{"itemIndex":6,"x":-169.5,"y":3.76890326,"z":33.0,"rx":0.0,"ry":22.0,"rz":0.0},{"itemIndex":6,"x":-166.5,"y":3.65841222,"z":33.0,"rx":0.0,"ry":345.0,"rz":0.0},{"itemIndex":6,"x":-159.0,"y":4.218209,"z":33.0,"rx":0.0,"ry":253.0,"rz":0.0},{"itemIndex":6,"x":-157.5,"y":4.25768232,"z":33.0,"rx":0.0,"ry":14.000001,"rz":0.0},{"itemIndex":6,"x":-145.5,"y":4.93511152,"z":33.0,"rx":0.0,"ry":153.0,"rz":0.0},{"itemIndex":6,"x":-144.0,"y":5.252989,"z":33.0,"rx":0.0,"ry":325.0,"rz":0.0},{"itemIndex":6,"x":-139.5,"y":6.10939646,"z":33.0,"rx":0.0,"ry":27.0000019,"rz":0.0},{"itemIndex":0,"x":-138.0,"y":6.29974365,"z":33.0,"rx":0.0,"ry":0.0,"rz":0.0},{"itemIndex":6,"x":-136.5,"y":6.40244675,"z":33.0,"rx":0.0,"ry":22.0,"rz":0.0},{"itemIndex":6,"x":-132.0,"y":6.674451,"z":33.0,"rx":0.0,"ry":195.0,"rz":0.0},{"itemIndex":6,"x":-130.5,"y":6.90305042,"z":33.0,"rx":0.0,"ry":259.0,"rz":0.0},{"itemIndex":6,"x":-127.5,"y":7.09319639,"z":33.0,"rx":0.0,"ry":350.0,"rz":0.0},{"itemIndex":6,"x":-118.5,"y":6.89457846,"z":33.0,"rx":0.0,"ry":178.0,"rz":0.0},{"itemIndex":6,"x":-112.5,"y":5.10062075,"z":33.0,"rx":0.0,"ry":160.0,"rz":0.0},{"itemIndex":6,"x":-108.0,"y":4.1206727,"z":33.0,"rx":0.0,"ry":92.99999,"rz":0.0},{"itemIndex":6,"x":-172.5,"y":4.34479952,"z":31.5,"rx":0.0,"ry":12.0,"rz":0.0},{"itemIndex":6,"x":-169.5,"y":3.67020583,"z":31.5,"rx":0.0,"ry":32.0,"rz":0.0},{"itemIndex":6,"x":-166.5,"y":3.511153,"z":31.5,"rx":0.0,"ry":154.0,"rz":0.0},{"itemIndex":6,"x":-163.5,"y":3.72201276,"z":31.5,"rx":0.0,"ry":114.0,"rz":0.0},{"itemIndex":6,"x":-153.0,"y":3.21780944,"z":31.5,"rx":0.0,"ry":118.0,"rz":0.0},{"itemIndex":6,"x":-147.0,"y":4.371274,"z":31.5,"rx":0.0,"ry":202.0,"rz":0.0},{"itemIndex":6,"x":-142.5,"y":5.348231,"z":31.5,"rx":0.0,"ry":290.0,"rz":0.0},{"itemIndex":6,"x":-135.0,"y":6.45105076,"z":31.5,"rx":0.0,"ry":25.9999981,"rz":0.0},{"itemIndex":6,"x":-133.5,"y":6.539199,"z":31.5,"rx":0.0,"ry":57.0,"rz":0.0},{"itemIndex":6,"x":-132.0,"y":6.470483,"z":31.5,"rx":0.0,"ry":204.0,"rz":0.0},{"itemIndex":6,"x":-130.5,"y":6.70231438,"z":31.5,"rx":0.0,"ry":219.0,"rz":0.0},{"itemIndex":6,"x":-127.5,"y":7.06588554,"z":31.5,"rx":0.0,"ry":43.9999962,"rz":0.0},{"itemIndex":6,"x":-126.0,"y":7.087206,"z":31.5,"rx":0.0,"ry":301.0,"rz":0.0},{"itemIndex":6,"x":-112.5,"y":4.63977242,"z":31.5,"rx":0.0,"ry":79.0,"rz":0.0},{"itemIndex":6,"x":-109.5,"y":4.0793004,"z":31.5,"rx":0.0,"ry":249.0,"rz":0.0},{"itemIndex":0,"x":-171.0,"y":3.87167358,"z":30.0,"rx":0.0,"ry":0.0,"rz":0.0},{"itemIndex":6,"x":-166.5,"y":3.363798,"z":30.0,"rx":0.0,"ry":135.0,"rz":0.0},{"itemIndex":6,"x":-163.5,"y":3.35280538,"z":30.0,"rx":0.0,"ry":355.0,"rz":0.0},{"itemIndex":6,"x":-157.5,"y":3.12420654,"z":30.0,"rx":0.0,"ry":68.0,"rz":0.0},{"itemIndex":6,"x":-151.5,"y":3.17994714,"z":30.0,"rx":0.0,"ry":328.0,"rz":0.0},{"itemIndex":6,"x":-144.0,"y":4.274068,"z":30.0,"rx":0.0,"ry":188.0,"rz":0.0},{"itemIndex":6,"x":-136.5,"y":6.132233,"z":30.0,"rx":0.0,"ry":114.0,"rz":0.0},{"itemIndex":6,"x":-132.0,"y":6.290697,"z":30.0,"rx":0.0,"ry":105.0,"rz":0.0},{"itemIndex":6,"x":-130.5,"y":6.576095,"z":30.0,"rx":0.0,"ry":192.0,"rz":0.0},{"itemIndex":6,"x":-126.0,"y":7.05245,"z":30.0,"rx":0.0,"ry":233.0,"rz":0.0},{"itemIndex":6,"x":-124.5,"y":6.87395859,"z":30.0,"rx":0.0,"ry":31.0000019,"rz":0.0},{"itemIndex":0,"x":-124.5,"y":6.8739624,"z":30.0,"rx":0.0,"ry":0.0,"rz":0.0},{"itemIndex":6,"x":-121.5,"y":7.18368959,"z":30.0,"rx":0.0,"ry":122.000008,"rz":0.0},{"itemIndex":6,"x":-120.0,"y":7.028356,"z":30.0,"rx":0.0,"ry":183.0,"rz":0.0},{"itemIndex":6,"x":-118.5,"y":6.590422,"z":30.0,"rx":0.0,"ry":6.0,"rz":0.0},{"itemIndex":6,"x":-114.0,"y":4.74208832,"z":30.0,"rx":0.0,"ry":191.0,"rz":0.0},{"itemIndex":6,"x":-111.0,"y":4.2471,"z":30.0,"rx":0.0,"ry":337.0,"rz":0.0},{"itemIndex":6,"x":-106.5,"y":3.38324976,"z":30.0,"rx":0.0,"ry":69.00001,"rz":0.0},{"itemIndex":6,"x":-168.0,"y":3.538109,"z":28.5,"rx":0.0,"ry":145.0,"rz":0.0},{"itemIndex":6,"x":-166.5,"y":3.29231024,"z":28.5,"rx":0.0,"ry":213.0,"rz":0.0},{"itemIndex":6,"x":-165.0,"y":3.15665078,"z":28.5,"rx":0.0,"ry":162.0,"rz":0.0},{"itemIndex":6,"x":-153.0,"y":2.815622,"z":28.5,"rx":0.0,"ry":94.0,"rz":0.0},{"itemIndex":6,"x":-148.5,"y":3.81400824,"z":28.5,"rx":0.0,"ry":312.0,"rz":0.0},{"itemIndex":1,"x":-148.5,"y":3.81401062,"z":28.5,"rx":0.0,"ry":0.0,"rz":0.0},{"itemIndex":6,"x":-147.0,"y":3.9712286,"z":28.5,"rx":0.0,"ry":246.0,"rz":0.0},{"itemIndex":0,"x":-145.5,"y":3.89341736,"z":28.5,"rx":0.0,"ry":0.0,"rz":0.0},{"itemIndex":6,"x":-135.0,"y":6.24228048,"z":28.5,"rx":0.0,"ry":104.0,"rz":0.0},{"itemIndex":6,"x":-132.0,"y":6.28007269,"z":28.5,"rx":0.0,"ry":160.0,"rz":0.0},{"itemIndex":6,"x":-130.5,"y":6.457508,"z":28.5,"rx":0.0,"ry":315.0,"rz":0.0},{"itemIndex":6,"x":-127.5,"y":6.830937,"z":28.5,"rx":0.0,"ry":325.0,"rz":0.0},{"itemIndex":6,"x":-123.0,"y":6.71733236,"z":28.5,"rx":0.0,"ry":228.0,"rz":0.0},{"itemIndex":6,"x":-120.0,"y":6.636806,"z":28.5,"rx":0.0,"ry":312.0,"rz":0.0},{"itemIndex":6,"x":-118.5,"y":6.307572,"z":28.5,"rx":0.0,"ry":90.0,"rz":0.0},{"itemIndex":6,"x":-115.5,"y":5.30375528,"z":28.5,"rx":0.0,"ry":102.0,"rz":0.0},{"itemIndex":6,"x":-111.0,"y":3.95687485,"z":28.5,"rx":0.0,"ry":257.0,"rz":0.0},{"itemIndex":6,"x":-108.0,"y":3.41461062,"z":28.5,"rx":0.0,"ry":315.0,"rz":0.0},{"itemIndex":6,"x":-169.5,"y":3.326142,"z":27.0,"rx":0.0,"ry":248.0,"rz":0.0},{"itemIndex":6,"x":-166.5,"y":3.248368,"z":27.0,"rx":0.0,"ry":148.0,"rz":0.0},{"itemIndex":6,"x":-156.0,"y":2.61105537,"z":27.0,"rx":0.0,"ry":45.0000038,"rz":0.0},{"itemIndex":6,"x":-153.0,"y":2.72765636,"z":27.0,"rx":0.0,"ry":221.0,"rz":0.0},{"itemIndex":6,"x":-144.0,"y":4.241894,"z":27.0,"rx":0.0,"ry":174.0,"rz":0.0},{"itemIndex":6,"x":-138.0,"y":5.93594933,"z":27.0,"rx":0.0,"ry":104.0,"rz":0.0},{"itemIndex":6,"x":-135.0,"y":6.25755548,"z":27.0,"rx":0.0,"ry":145.0,"rz":0.0},{"itemIndex":6,"x":-118.5,"y":6.129583,"z":27.0,"rx":0.0,"ry":23.0,"rz":0.0},{"itemIndex":6,"x":-117.0,"y":5.61246538,"z":27.0,"rx":0.0,"ry":277.0,"rz":0.0},{"itemIndex":6,"x":-111.0,"y":3.63670349,"z":27.0,"rx":0.0,"ry":13.0,"rz":0.0},{"itemIndex":6,"x":-108.0,"y":3.04675031,"z":27.0,"rx":0.0,"ry":99.0,"rz":0.0},{"itemIndex":6,"x":-105.0,"y":2.61979413,"z":27.0,"rx":0.0,"ry":86.99999,"rz":0.0},{"itemIndex":6,"x":-160.5,"y":2.60034752,"z":25.5,"rx":0.0,"ry":64.0,"rz":0.0},{"itemIndex":6,"x":-159.0,"y":2.546985,"z":25.5,"rx":0.0,"ry":277.0,"rz":0.0},{"itemIndex":6,"x":-150.0,"y":3.043074,"z":25.5,"rx":0.0,"ry":279.0,"rz":0.0},{"itemIndex":6,"x":-145.5,"y":4.067538,"z":25.5,"rx":0.0,"ry":160.0,"rz":0.0},{"itemIndex":6,"x":-144.0,"y":4.488125,"z":25.5,"rx":0.0,"ry":83.0,"rz":0.0},{"itemIndex":6,"x":-142.5,"y":4.775311,"z":25.5,"rx":0.0,"ry":119.0,"rz":0.0},{"itemIndex":6,"x":-141.0,"y":5.187933,"z":25.5,"rx":0.0,"ry":115.000008,"rz":0.0},{"itemIndex":6,"x":-135.0,"y":6.104971,"z":25.5,"rx":0.0,"ry":337.0,"rz":0.0},{"itemIndex":6,"x":-127.5,"y":7.035299,"z":25.5,"rx":0.0,"ry":49.0000038,"rz":0.0},{"itemIndex":6,"x":-115.5,"y":4.94716167,"z":25.5,"rx":0.0,"ry":302.0,"rz":0.0},{"itemIndex":6,"x":-112.5,"y":3.80475688,"z":25.5,"rx":0.0,"ry":286.0,"rz":0.0},{"itemIndex":6,"x":-106.5,"y":2.8191545,"z":25.5,"rx":0.0,"ry":274.0,"rz":0.0},{"itemIndex":6,"x":-105.0,"y":2.70868683,"z":25.5,"rx":0.0,"ry":18.9999962,"rz":0.0},{"itemIndex":6,"x":-159.0,"y":2.46095967,"z":24.0,"rx":0.0,"ry":280.0,"rz":0.0},{"itemIndex":6,"x":-157.5,"y":2.356086,"z":24.0,"rx":0.0,"ry":324.0,"rz":0.0},{"itemIndex":6,"x":-150.0,"y":2.78117943,"z":24.0,"rx":0.0,"ry":141.0,"rz":0.0},{"itemIndex":6,"x":-148.5,"y":3.32118225,"z":24.0,"rx":0.0,"ry":41.0,"rz":0.0},{"itemIndex":6,"x":-147.0,"y":3.83369422,"z":24.0,"rx":0.0,"ry":164.0,"rz":0.0},{"itemIndex":6,"x":-144.0,"y":4.564121,"z":24.0,"rx":0.0,"ry":287.0,"rz":0.0},{"itemIndex":6,"x":-141.0,"y":5.23831558,"z":24.0,"rx":0.0,"ry":189.0,"rz":0.0},{"itemIndex":6,"x":-133.5,"y":6.11047268,"z":24.0,"rx":0.0,"ry":61.9999962,"rz":0.0},{"itemIndex":6,"x":-123.0,"y":7.095702,"z":24.0,"rx":0.0,"ry":289.0,"rz":0.0},{"itemIndex":6,"x":-115.5,"y":4.88706064,"z":24.0,"rx":0.0,"ry":206.0,"rz":0.0},{"itemIndex":6,"x":-111.0,"y":3.37615013,"z":24.0,"rx":0.0,"ry":350.0,"rz":0.0},{"itemIndex":6,"x":-106.5,"y":3.11039233,"z":24.0,"rx":0.0,"ry":200.0,"rz":0.0},{"itemIndex":6,"x":-168.0,"y":2.49124575,"z":22.5,"rx":0.0,"ry":359.0,"rz":0.0},{"itemIndex":6,"x":-151.5,"y":2.36450863,"z":22.5,"rx":0.0,"ry":153.0,"rz":0.0},{"itemIndex":6,"x":-148.5,"y":3.44215369,"z":22.5,"rx":0.0,"ry":265.0,"rz":0.0},{"itemIndex":6,"x":-147.0,"y":3.8680284,"z":22.5,"rx":0.0,"ry":293.0,"rz":0.0},{"itemIndex":6,"x":-145.5,"y":4.1914463,"z":22.5,"rx":0.0,"ry":203.0,"rz":0.0},{"itemIndex":6,"x":-142.5,"y":4.845176,"z":22.5,"rx":0.0,"ry":71.99999,"rz":0.0},{"itemIndex":6,"x":-138.0,"y":5.38372564,"z":22.5,"rx":0.0,"ry":258.0,"rz":0.0},{"itemIndex":6,"x":-135.0,"y":6.227451,"z":22.5,"rx":0.0,"ry":319.0,"rz":0.0},{"itemIndex":0,"x":-133.5,"y":6.231888,"z":22.5,"rx":0.0,"ry":0.0,"rz":0.0},{"itemIndex":6,"x":-132.0,"y":6.603541,"z":22.5,"rx":0.0,"ry":189.0,"rz":0.0},{"itemIndex":6,"x":-127.5,"y":7.653901,"z":22.5,"rx":0.0,"ry":148.0,"rz":0.0},{"itemIndex":6,"x":-126.0,"y":7.754725,"z":22.5,"rx":0.0,"ry":293.0,"rz":0.0},{"itemIndex":6,"x":-120.0,"y":6.84281445,"z":22.5,"rx":0.0,"ry":152.0,"rz":0.0},{"itemIndex":6,"x":-115.5,"y":5.125538,"z":22.5,"rx":0.0,"ry":47.0,"rz":0.0},{"itemIndex":6,"x":-114.0,"y":4.596341,"z":22.5,"rx":0.0,"ry":311.0,"rz":0.0},{"itemIndex":0,"x":-109.5,"y":3.221634,"z":22.5,"rx":0.0,"ry":0.0,"rz":0.0},{"itemIndex":6,"x":-105.0,"y":3.31628275,"z":22.5,"rx":0.0,"ry":41.0,"rz":0.0},{"itemIndex":6,"x":-171.0,"y":2.7595818,"z":21.0,"rx":0.0,"ry":3.99999952,"rz":0.0},{"itemIndex":6,"x":-169.5,"y":2.50668287,"z":21.0,"rx":0.0,"ry":139.0,"rz":0.0},{"itemIndex":6,"x":-165.0,"y":2.77738976,"z":21.0,"rx":0.0,"ry":244.0,"rz":0.0},{"itemIndex":6,"x":-163.5,"y":2.820233,"z":21.0,"rx":0.0,"ry":306.0,"rz":0.0},{"itemIndex":6,"x":-162.0,"y":2.78673983,"z":21.0,"rx":0.0,"ry":18.9999962,"rz":0.0},{"itemIndex":6,"x":-157.5,"y":2.1811924,"z":21.0,"rx":0.0,"ry":63.0,"rz":0.0},{"itemIndex":6,"x":-150.0,"y":3.11145282,"z":21.0,"rx":0.0,"ry":263.0,"rz":0.0},{"itemIndex":6,"x":-147.0,"y":3.93283439,"z":21.0,"rx":0.0,"ry":59.0,"rz":0.0},{"itemIndex":6,"x":-141.0,"y":4.93715334,"z":21.0,"rx":0.0,"ry":77.0,"rz":0.0},{"itemIndex":1,"x":-141.0,"y":4.937149,"z":21.0,"rx":0.0,"ry":0.0,"rz":0.0},{"itemIndex":0,"x":-132.0,"y":6.95863342,"z":21.0,"rx":0.0,"ry":0.0,"rz":0.0},{"itemIndex":6,"x":-127.5,"y":7.636471,"z":21.0,"rx":0.0,"ry":182.0,"rz":0.0},{"itemIndex":6,"x":-124.5,"y":7.839242,"z":21.0,"rx":0.0,"ry":232.0,"rz":0.0},{"itemIndex":6,"x":-123.0,"y":7.31380749,"z":21.0,"rx":0.0,"ry":236.0,"rz":0.0},{"itemIndex":6,"x":-121.5,"y":7.01488352,"z":21.0,"rx":0.0,"ry":333.0,"rz":0.0},{"itemIndex":6,"x":-115.5,"y":5.490728,"z":21.0,"rx":0.0,"ry":264.0,"rz":0.0},{"itemIndex":0,"x":-115.5,"y":5.49072266,"z":21.0,"rx":0.0,"ry":0.0,"rz":0.0},{"itemIndex":6,"x":-111.0,"y":3.88168478,"z":21.0,"rx":0.0,"ry":229.0,"rz":0.0},{"itemIndex":6,"x":-109.5,"y":3.40000772,"z":21.0,"rx":0.0,"ry":7.999999,"rz":0.0},{"itemIndex":6,"x":-169.5,"y":2.40846252,"z":19.5,"rx":0.0,"ry":192.0,"rz":0.0},{"itemIndex":6,"x":-154.5,"y":2.20596147,"z":19.5,"rx":0.0,"ry":344.0,"rz":0.0},{"itemIndex":6,"x":-150.0,"y":3.12588525,"z":19.5,"rx":0.0,"ry":120.000008,"rz":0.0},{"itemIndex":6,"x":-139.5,"y":5.079453,"z":19.5,"rx":0.0,"ry":357.0,"rz":0.0},{"itemIndex":6,"x":-138.0,"y":5.6228075,"z":19.5,"rx":0.0,"ry":162.0,"rz":0.0},{"itemIndex":6,"x":-135.0,"y":6.6972065,"z":19.5,"rx":0.0,"ry":152.0,"rz":0.0},{"itemIndex":6,"x":-133.5,"y":6.969822,"z":19.5,"rx":0.0,"ry":3.0,"rz":0.0},{"itemIndex":6,"x":-124.5,"y":7.751378,"z":19.5,"rx":0.0,"ry":250.0,"rz":0.0},{"itemIndex":6,"x":-120.0,"y":6.78710032,"z":19.5,"rx":0.0,"ry":48.0,"rz":0.0},{"itemIndex":6,"x":-118.5,"y":6.50747061,"z":19.5,"rx":0.0,"ry":133.0,"rz":0.0},{"itemIndex":6,"x":-114.0,"y":5.304636,"z":19.5,"rx":0.0,"ry":204.0,"rz":0.0},{"itemIndex":6,"x":-172.5,"y":3.05968332,"z":18.0,"rx":0.0,"ry":262.0,"rz":0.0},{"itemIndex":6,"x":-166.5,"y":2.423785,"z":18.0,"rx":0.0,"ry":14.000001,"rz":0.0},{"itemIndex":6,"x":-163.5,"y":2.60092115,"z":18.0,"rx":0.0,"ry":25.0,"rz":0.0},{"itemIndex":6,"x":-153.0,"y":2.340107,"z":18.0,"rx":0.0,"ry":28.0000019,"rz":0.0},{"itemIndex":6,"x":-151.5,"y":2.59652877,"z":18.0,"rx":0.0,"ry":189.0,"rz":0.0},{"itemIndex":6,"x":-150.0,"y":2.83120728,"z":18.0,"rx":0.0,"ry":192.0,"rz":0.0},{"itemIndex":6,"x":-148.5,"y":3.3349936,"z":18.0,"rx":0.0,"ry":238.0,"rz":0.0},{"itemIndex":6,"x":-145.5,"y":4.0342865,"z":18.0,"rx":0.0,"ry":67.0,"rz":0.0},{"itemIndex":6,"x":-144.0,"y":4.33175945,"z":18.0,"rx":0.0,"ry":311.0,"rz":0.0},{"itemIndex":0,"x":-144.0,"y":4.33175659,"z":18.0,"rx":0.0,"ry":0.0,"rz":0.0},{"itemIndex":6,"x":-139.5,"y":5.21751642,"z":18.0,"rx":0.0,"ry":28.0000019,"rz":0.0},{"itemIndex":6,"x":-136.5,"y":6.05410576,"z":18.0,"rx":0.0,"ry":18.0000019,"rz":0.0},{"itemIndex":6,"x":-135.0,"y":6.60973167,"z":18.0,"rx":0.0,"ry":287.0,"rz":0.0},{"itemIndex":6,"x":-126.0,"y":8.20716,"z":18.0,"rx":0.0,"ry":42.0,"rz":0.0},{"itemIndex":6,"x":-124.5,"y":7.867312,"z":18.0,"rx":0.0,"ry":7.00000048,"rz":0.0},{"itemIndex":6,"x":-120.0,"y":6.79593039,"z":18.0,"rx":0.0,"ry":226.0,"rz":0.0},{"itemIndex":6,"x":-105.0,"y":4.96458149,"z":18.0,"rx":0.0,"ry":150.0,"rz":0.0},{"itemIndex":6,"x":-171.0,"y":3.05805659,"z":16.5,"rx":0.0,"ry":32.0,"rz":0.0},{"itemIndex":6,"x":-163.5,"y":2.42465425,"z":16.5,"rx":0.0,"ry":163.0,"rz":0.0},{"itemIndex":6,"x":-156.0,"y":2.48657846,"z":16.5,"rx":0.0,"ry":325.0,"rz":0.0},{"itemIndex":6,"x":-145.5,"y":4.14226151,"z":16.5,"rx":0.0,"ry":201.0,"rz":0.0},{"itemIndex":6,"x":-142.5,"y":4.75272846,"z":16.5,"rx":0.0,"ry":140.0,"rz":0.0},{"itemIndex":6,"x":-141.0,"y":5.10010052,"z":16.5,"rx":0.0,"ry":166.0,"rz":0.0},{"itemIndex":6,"x":-139.5,"y":5.1187644,"z":16.5,"rx":0.0,"ry":338.0,"rz":0.0},{"itemIndex":6,"x":-135.0,"y":6.889383,"z":16.5,"rx":0.0,"ry":23.0,"rz":0.0},{"itemIndex":6,"x":-132.0,"y":7.93153858,"z":16.5,"rx":0.0,"ry":306.0,"rz":0.0},{"itemIndex":6,"x":-129.0,"y":8.534788,"z":16.5,"rx":0.0,"ry":45.0000038,"rz":0.0},{"itemIndex":6,"x":-118.5,"y":6.427841,"z":16.5,"rx":0.0,"ry":298.0,"rz":0.0},{"itemIndex":6,"x":-109.5,"y":5.21418047,"z":16.5,"rx":0.0,"ry":164.0,"rz":0.0},{"itemIndex":6,"x":-171.0,"y":3.08470869,"z":15.0,"rx":0.0,"ry":269.0,"rz":0.0},{"itemIndex":6,"x":-166.5,"y":2.53501344,"z":15.0,"rx":0.0,"ry":180.0,"rz":0.0},{"itemIndex":0,"x":-151.5,"y":2.609497,"z":15.0,"rx":0.0,"ry":0.0,"rz":0.0},{"itemIndex":6,"x":-150.0,"y":3.03903365,"z":15.0,"rx":0.0,"ry":59.0,"rz":0.0},{"itemIndex":6,"x":-145.5,"y":4.11763954,"z":15.0,"rx":0.0,"ry":175.0,"rz":0.0},{"itemIndex":6,"x":-144.0,"y":4.41366053,"z":15.0,"rx":0.0,"ry":221.0,"rz":0.0},{"itemIndex":6,"x":-142.5,"y":4.782243,"z":15.0,"rx":0.0,"ry":334.0,"rz":0.0},{"itemIndex":6,"x":-135.0,"y":7.036679,"z":15.0,"rx":0.0,"ry":346.0,"rz":0.0},{"itemIndex":6,"x":-133.5,"y":7.71465635,"z":15.0,"rx":0.0,"ry":9.000001,"rz":0.0},{"itemIndex":6,"x":-127.5,"y":8.395209,"z":15.0,"rx":0.0,"ry":212.0,"rz":0.0},{"itemIndex":6,"x":-123.0,"y":7.5763135,"z":15.0,"rx":0.0,"ry":196.0,"rz":0.0},{"itemIndex":6,"x":-120.0,"y":7.0000205,"z":15.0,"rx":0.0,"ry":241.0,"rz":0.0},{"itemIndex":6,"x":-118.5,"y":6.89439964,"z":15.0,"rx":0.0,"ry":91.00001,"rz":0.0},{"itemIndex":6,"x":-117.0,"y":6.69433,"z":15.0,"rx":0.0,"ry":138.0,"rz":0.0},{"itemIndex":6,"x":-108.0,"y":5.79219246,"z":15.0,"rx":0.0,"ry":309.0,"rz":0.0},{"itemIndex":6,"x":-105.0,"y":6.272316,"z":15.0,"rx":0.0,"ry":162.0,"rz":0.0},{"itemIndex":6,"x":-162.0,"y":2.70021152,"z":13.5,"rx":0.0,"ry":47.0,"rz":0.0},{"itemIndex":6,"x":-159.0,"y":2.94771934,"z":13.5,"rx":0.0,"ry":277.0,"rz":0.0},{"itemIndex":6,"x":-157.5,"y":2.67700863,"z":13.5,"rx":0.0,"ry":107.0,"rz":0.0},{"itemIndex":6,"x":-156.0,"y":2.58587122,"z":13.5,"rx":0.0,"ry":345.0,"rz":0.0},{"itemIndex":6,"x":-153.0,"y":2.49412274,"z":13.5,"rx":0.0,"ry":145.0,"rz":0.0},{"itemIndex":6,"x":-147.0,"y":3.70316768,"z":13.5,"rx":0.0,"ry":157.0,"rz":0.0},{"itemIndex":6,"x":-142.5,"y":4.87553,"z":13.5,"rx":0.0,"ry":276.0,"rz":0.0},{"itemIndex":6,"x":-141.0,"y":5.122465,"z":13.5,"rx":0.0,"ry":208.0,"rz":0.0},{"itemIndex":6,"x":-138.0,"y":6.053788,"z":13.5,"rx":0.0,"ry":219.0,"rz":0.0},{"itemIndex":6,"x":-136.5,"y":6.790216,"z":13.5,"rx":0.0,"ry":85.0,"rz":0.0},{"itemIndex":6,"x":-133.5,"y":7.894341,"z":13.5,"rx":0.0,"ry":313.0,"rz":0.0},{"itemIndex":6,"x":-130.5,"y":8.447569,"z":13.5,"rx":0.0,"ry":349.0,"rz":0.0},{"itemIndex":6,"x":-126.0,"y":7.995636,"z":13.5,"rx":0.0,"ry":90.0,"rz":0.0},{"itemIndex":6,"x":-124.5,"y":7.89950752,"z":13.5,"rx":0.0,"ry":18.0000019,"rz":0.0},{"itemIndex":6,"x":-115.5,"y":6.877671,"z":13.5,"rx":0.0,"ry":187.0,"rz":0.0},{"itemIndex":6,"x":-114.0,"y":6.82216072,"z":13.5,"rx":0.0,"ry":116.0,"rz":0.0},{"itemIndex":6,"x":-111.0,"y":6.53761053,"z":13.5,"rx":0.0,"ry":338.0,"rz":0.0},{"itemIndex":6,"x":-109.5,"y":6.43072653,"z":13.5,"rx":0.0,"ry":138.0,"rz":0.0},{"itemIndex":6,"x":-166.5,"y":2.76675,"z":12.0,"rx":0.0,"ry":144.0,"rz":0.0},{"itemIndex":6,"x":-163.5,"y":2.9027245,"z":12.0,"rx":0.0,"ry":97.0,"rz":0.0},{"itemIndex":6,"x":-157.5,"y":3.03076363,"z":12.0,"rx":0.0,"ry":236.0,"rz":0.0},{"itemIndex":6,"x":-156.0,"y":2.84408712,"z":12.0,"rx":0.0,"ry":218.0,"rz":0.0},{"itemIndex":6,"x":-154.5,"y":2.81826735,"z":12.0,"rx":0.0,"ry":175.0,"rz":0.0},{"itemIndex":6,"x":-150.0,"y":3.32371736,"z":12.0,"rx":0.0,"ry":90.0,"rz":0.0},{"itemIndex":6,"x":-144.0,"y":4.770998,"z":12.0,"rx":0.0,"ry":347.0,"rz":0.0},{"itemIndex":6,"x":-139.5,"y":6.096515,"z":12.0,"rx":0.0,"ry":352.0,"rz":0.0},{"itemIndex":6,"x":-130.5,"y":8.490284,"z":12.0,"rx":0.0,"ry":28.0000019,"rz":0.0},{"itemIndex":6,"x":-129.0,"y":8.275643,"z":12.0,"rx":0.0,"ry":322.0,"rz":0.0},{"itemIndex":6,"x":-127.5,"y":8.347265,"z":12.0,"rx":0.0,"ry":256.0,"rz":0.0},{"itemIndex":6,"x":-123.0,"y":8.216246,"z":12.0,"rx":0.0,"ry":104.0,"rz":0.0},{"itemIndex":6,"x":-120.0,"y":8.013895,"z":12.0,"rx":0.0,"ry":317.0,"rz":0.0},{"itemIndex":6,"x":-115.5,"y":7.407622,"z":12.0,"rx":0.0,"ry":36.0,"rz":0.0},{"itemIndex":6,"x":-114.0,"y":7.41292238,"z":12.0,"rx":0.0,"ry":159.0,"rz":0.0},{"itemIndex":6,"x":-112.5,"y":7.34741354,"z":12.0,"rx":0.0,"ry":280.0,"rz":0.0},{"itemIndex":6,"x":-109.5,"y":6.962121,"z":12.0,"rx":0.0,"ry":140.0,"rz":0.0},{"itemIndex":6,"x":-108.0,"y":7.036764,"z":12.0,"rx":0.0,"ry":232.0,"rz":0.0},{"itemIndex":6,"x":-106.5,"y":7.501876,"z":12.0,"rx":0.0,"ry":351.0,"rz":0.0},{"itemIndex":6,"x":-105.0,"y":7.66359949,"z":12.0,"rx":0.0,"ry":125.0,"rz":0.0},{"itemIndex":6,"x":-172.5,"y":3.097173,"z":10.5,"rx":0.0,"ry":314.0,"rz":0.0},{"itemIndex":6,"x":-171.0,"y":3.13303447,"z":10.5,"rx":0.0,"ry":14.000001,"rz":0.0},{"itemIndex":6,"x":-166.5,"y":2.89236426,"z":10.5,"rx":0.0,"ry":46.0,"rz":0.0},{"itemIndex":6,"x":-162.0,"y":3.122913,"z":10.5,"rx":0.0,"ry":104.0,"rz":0.0},{"itemIndex":6,"x":-159.0,"y":3.2290988,"z":10.5,"rx":0.0,"ry":63.0,"rz":0.0},{"itemIndex":6,"x":-156.0,"y":3.24712968,"z":10.5,"rx":0.0,"ry":358.0,"rz":0.0},{"itemIndex":6,"x":-145.5,"y":4.8087945,"z":10.5,"rx":0.0,"ry":97.0,"rz":0.0},{"itemIndex":6,"x":-141.0,"y":6.30001163,"z":10.5,"rx":0.0,"ry":65.00001,"rz":0.0},{"itemIndex":6,"x":-139.5,"y":6.809601,"z":10.5,"rx":0.0,"ry":92.0,"rz":0.0},{"itemIndex":6,"x":-132.0,"y":8.885089,"z":10.5,"rx":0.0,"ry":60.0000038,"rz":0.0},{"itemIndex":6,"x":-127.5,"y":8.594925,"z":10.5,"rx":0.0,"ry":71.0,"rz":0.0},{"itemIndex":6,"x":-121.5,"y":8.72221,"z":10.5,"rx":0.0,"ry":50.0000038,"rz":0.0},{"itemIndex":6,"x":-120.0,"y":8.581932,"z":10.5,"rx":0.0,"ry":180.0,"rz":0.0},{"itemIndex":6,"x":-118.5,"y":8.31808,"z":10.5,"rx":0.0,"ry":181.0,"rz":0.0},{"itemIndex":6,"x":-109.5,"y":7.57590246,"z":10.5,"rx":0.0,"ry":293.0,"rz":0.0},{"itemIndex":6,"x":-106.5,"y":8.008575,"z":10.5,"rx":0.0,"ry":198.0,"rz":0.0},{"itemIndex":6,"x":-105.0,"y":8.616701,"z":10.5,"rx":0.0,"ry":296.0,"rz":0.0},{"itemIndex":6,"x":-172.5,"y":3.09634638,"z":9.0,"rx":0.0,"ry":273.0,"rz":0.0},{"itemIndex":6,"x":-171.0,"y":2.99509668,"z":9.0,"rx":0.0,"ry":299.0,"rz":0.0},{"itemIndex":6,"x":-168.0,"y":3.042434,"z":9.0,"rx":0.0,"ry":166.0,"rz":0.0},{"itemIndex":6,"x":-157.5,"y":3.691948,"z":9.0,"rx":0.0,"ry":158.0,"rz":0.0},{"itemIndex":6,"x":-153.0,"y":3.48224735,"z":9.0,"rx":0.0,"ry":277.0,"rz":0.0},{"itemIndex":6,"x":-151.5,"y":3.44748163,"z":9.0,"rx":0.0,"ry":138.0,"rz":0.0},{"itemIndex":6,"x":-145.5,"y":5.167559,"z":9.0,"rx":0.0,"ry":342.0,"rz":0.0},{"itemIndex":6,"x":-144.0,"y":5.628063,"z":9.0,"rx":0.0,"ry":181.0,"rz":0.0},{"itemIndex":6,"x":-142.5,"y":6.20558167,"z":9.0,"rx":0.0,"ry":113.0,"rz":0.0},{"itemIndex":6,"x":-139.5,"y":7.2808156,"z":9.0,"rx":0.0,"ry":99.99999,"rz":0.0},{"itemIndex":6,"x":-132.0,"y":9.040901,"z":9.0,"rx":0.0,"ry":290.0,"rz":0.0},{"itemIndex":6,"x":-124.5,"y":9.366468,"z":9.0,"rx":0.0,"ry":271.0,"rz":0.0},{"itemIndex":6,"x":-123.0,"y":9.257647,"z":9.0,"rx":0.0,"ry":227.0,"rz":0.0},{"itemIndex":6,"x":-114.0,"y":8.79482,"z":9.0,"rx":0.0,"ry":14.000001,"rz":0.0},{"itemIndex":6,"x":-105.0,"y":9.003318,"z":9.0,"rx":0.0,"ry":17.0,"rz":0.0},{"itemIndex":6,"x":-172.5,"y":2.8669734,"z":7.5,"rx":0.0,"ry":347.0,"rz":0.0},{"itemIndex":6,"x":-166.5,"y":3.55285,"z":7.5,"rx":0.0,"ry":344.0,"rz":0.0},{"itemIndex":6,"x":-160.5,"y":3.320333,"z":7.5,"rx":0.0,"ry":3.0,"rz":0.0},{"itemIndex":6,"x":-153.0,"y":3.85339546,"z":7.5,"rx":0.0,"ry":60.0000038,"rz":0.0},{"itemIndex":6,"x":-144.0,"y":6.18010139,"z":7.5,"rx":0.0,"ry":328.0,"rz":0.0},{"itemIndex":6,"x":-142.5,"y":6.71291637,"z":7.5,"rx":0.0,"ry":266.0,"rz":0.0},{"itemIndex":6,"x":-127.5,"y":9.005999,"z":7.5,"rx":0.0,"ry":323.0,"rz":0.0},{"itemIndex":6,"x":-126.0,"y":9.238241,"z":7.5,"rx":0.0,"ry":135.0,"rz":0.0},{"itemIndex":6,"x":-120.0,"y":9.886796,"z":7.5,"rx":0.0,"ry":166.0,"rz":0.0},{"itemIndex":6,"x":-117.0,"y":9.861206,"z":7.5,"rx":0.0,"ry":43.9999962,"rz":0.0},{"itemIndex":6,"x":-115.5,"y":9.601524,"z":7.5,"rx":0.0,"ry":86.0,"rz":0.0},{"itemIndex":6,"x":-114.0,"y":9.460845,"z":7.5,"rx":0.0,"ry":312.0,"rz":0.0},{"itemIndex":0,"x":-114.0,"y":9.460846,"z":7.5,"rx":0.0,"ry":0.0,"rz":0.0},{"itemIndex":6,"x":-166.5,"y":3.71736741,"z":6.0,"rx":0.0,"ry":173.0,"rz":0.0},{"itemIndex":6,"x":-165.0,"y":3.51202464,"z":6.0,"rx":0.0,"ry":168.0,"rz":0.0},{"itemIndex":6,"x":-157.5,"y":3.88510728,"z":6.0,"rx":0.0,"ry":121.0,"rz":0.0},{"itemIndex":6,"x":-147.0,"y":5.82998133,"z":6.0,"rx":0.0,"ry":153.0,"rz":0.0},{"itemIndex":6,"x":-144.0,"y":6.64687443,"z":6.0,"rx":0.0,"ry":71.99999,"rz":0.0},{"itemIndex":6,"x":-141.0,"y":7.93798637,"z":6.0,"rx":0.0,"ry":120.000008,"rz":0.0},{"itemIndex":6,"x":-135.0,"y":9.430324,"z":6.0,"rx":0.0,"ry":38.0,"rz":0.0},{"itemIndex":6,"x":-129.0,"y":9.488209,"z":6.0,"rx":0.0,"ry":165.0,"rz":0.0},{"itemIndex":6,"x":-123.0,"y":9.852385,"z":6.0,"rx":0.0,"ry":265.0,"rz":0.0},{"itemIndex":6,"x":-120.0,"y":10.342761,"z":6.0,"rx":0.0,"ry":1.0,"rz":0.0},{"itemIndex":6,"x":-117.0,"y":10.2002134,"z":6.0,"rx":0.0,"ry":168.0,"rz":0.0},{"itemIndex":6,"x":-114.0,"y":9.6888895,"z":6.0,"rx":0.0,"ry":22.0,"rz":0.0},{"itemIndex":6,"x":-111.0,"y":9.5593195,"z":6.0,"rx":0.0,"ry":73.99999,"rz":0.0},{"itemIndex":6,"x":-109.5,"y":9.397927,"z":6.0,"rx":0.0,"ry":148.0,"rz":0.0},{"itemIndex":6,"x":-108.0,"y":9.244776,"z":6.0,"rx":0.0,"ry":300.0,"rz":0.0},{"itemIndex":6,"x":-169.5,"y":3.618673,"z":4.500002,"rx":0.0,"ry":345.0,"rz":0.0},{"itemIndex":6,"x":-168.0,"y":3.711089,"z":4.500002,"rx":0.0,"ry":202.0,"rz":0.0},{"itemIndex":6,"x":-165.0,"y":3.6735692,"z":4.500002,"rx":0.0,"ry":237.0,"rz":0.0},{"itemIndex":6,"x":-163.5,"y":3.601333,"z":4.500002,"rx":0.0,"ry":43.0,"rz":0.0},{"itemIndex":6,"x":-160.5,"y":3.61027813,"z":4.500002,"rx":0.0,"ry":303.0,"rz":0.0},{"itemIndex":6,"x":-144.0,"y":7.36701155,"z":4.500002,"rx":0.0,"ry":245.0,"rz":0.0},{"itemIndex":6,"x":-138.0,"y":9.524987,"z":4.500002,"rx":0.0,"ry":336.0,"rz":0.0},{"itemIndex":6,"x":-132.0,"y":9.97147751,"z":4.500002,"rx":0.0,"ry":195.0,"rz":0.0},{"itemIndex":6,"x":-129.0,"y":9.571327,"z":4.500002,"rx":0.0,"ry":322.0,"rz":0.0},{"itemIndex":6,"x":-127.5,"y":9.597084,"z":4.500002,"rx":0.0,"ry":7.00000048,"rz":0.0},{"itemIndex":6,"x":-126.0,"y":9.637113,"z":4.500002,"rx":0.0,"ry":315.0,"rz":0.0},{"itemIndex":6,"x":-117.0,"y":10.3201342,"z":4.500002,"rx":0.0,"ry":138.0,"rz":0.0},{"itemIndex":6,"x":-111.0,"y":9.830691,"z":4.500002,"rx":0.0,"ry":78.0,"rz":0.0},{"itemIndex":6,"x":-109.5,"y":9.759744,"z":4.500002,"rx":0.0,"ry":295.0,"rz":0.0},{"itemIndex":6,"x":-108.0,"y":9.502229,"z":4.500002,"rx":0.0,"ry":150.0,"rz":0.0},{"itemIndex":6,"x":-171.0,"y":3.53764629,"z":3.0,"rx":0.0,"ry":338.0,"rz":0.0},{"itemIndex":6,"x":-169.5,"y":3.65942216,"z":3.0,"rx":0.0,"ry":57.0,"rz":0.0},{"itemIndex":6,"x":-168.0,"y":3.67284918,"z":3.0,"rx":0.0,"ry":140.0,"rz":0.0},{"itemIndex":6,"x":-156.0,"y":4.247952,"z":3.0,"rx":0.0,"ry":246.0,"rz":0.0},{"itemIndex":6,"x":-153.0,"y":4.727631,"z":3.0,"rx":0.0,"ry":91.00001,"rz":0.0},{"itemIndex":6,"x":-147.0,"y":6.64863443,"z":3.0,"rx":0.0,"ry":306.0,"rz":0.0},{"itemIndex":6,"x":-145.5,"y":7.163069,"z":3.0,"rx":0.0,"ry":38.0,"rz":0.0},{"itemIndex":6,"x":-144.0,"y":7.957911,"z":3.0,"rx":0.0,"ry":57.0,"rz":0.0},{"itemIndex":6,"x":-139.5,"y":9.547125,"z":3.0,"rx":0.0,"ry":180.0,"rz":0.0},{"itemIndex":6,"x":-138.0,"y":9.958278,"z":3.0,"rx":0.0,"ry":25.9999981,"rz":0.0},{"itemIndex":6,"x":-136.5,"y":10.0889053,"z":3.0,"rx":0.0,"ry":140.0,"rz":0.0},{"itemIndex":0,"x":-133.5,"y":10.3801422,"z":3.0,"rx":0.0,"ry":0.0,"rz":0.0},{"itemIndex":6,"x":-132.0,"y":10.20023,"z":3.0,"rx":0.0,"ry":187.0,"rz":0.0},{"itemIndex":6,"x":-130.5,"y":9.996979,"z":3.0,"rx":0.0,"ry":77.0,"rz":0.0},{"itemIndex":6,"x":-126.0,"y":9.884525,"z":3.0,"rx":0.0,"ry":151.0,"rz":0.0},{"itemIndex":6,"x":-121.5,"y":10.2486591,"z":3.0,"rx":0.0,"ry":18.0000019,"rz":0.0},{"itemIndex":6,"x":-120.0,"y":10.4445019,"z":3.0,"rx":0.0,"ry":211.0,"rz":0.0},{"itemIndex":6,"x":-118.5,"y":10.5045128,"z":3.0,"rx":0.0,"ry":66.0,"rz":0.0},{"itemIndex":6,"x":-117.0,"y":10.4201136,"z":3.0,"rx":0.0,"ry":170.0,"rz":0.0},{"itemIndex":6,"x":-115.5,"y":10.3036585,"z":3.0,"rx":0.0,"ry":273.0,"rz":0.0},{"itemIndex":6,"x":-114.0,"y":10.3471632,"z":3.0,"rx":0.0,"ry":340.0,"rz":0.0},{"itemIndex":6,"x":-106.5,"y":9.896026,"z":3.0,"rx":0.0,"ry":315.0,"rz":0.0},{"itemIndex":6,"x":-169.5,"y":3.66266084,"z":1.5,"rx":0.0,"ry":240.0,"rz":0.0},{"itemIndex":6,"x":-165.0,"y":3.431496,"z":1.5,"rx":0.0,"ry":338.0,"rz":0.0},{"itemIndex":6,"x":-156.0,"y":4.525592,"z":1.5,"rx":0.0,"ry":331.0,"rz":0.0},{"itemIndex":6,"x":-154.5,"y":4.888374,"z":1.5,"rx":0.0,"ry":109.0,"rz":0.0},{"itemIndex":0,"x":-139.5,"y":9.912445,"z":1.5,"rx":0.0,"ry":0.0,"rz":0.0},{"itemIndex":6,"x":-132.0,"y":10.39477,"z":1.5,"rx":0.0,"ry":18.0000019,"rz":0.0},{"itemIndex":6,"x":-126.0,"y":10.2861042,"z":1.5,"rx":0.0,"ry":278.0,"rz":0.0},{"itemIndex":6,"x":-109.5,"y":10.3091412,"z":1.5,"rx":0.0,"ry":258.0,"rz":0.0},{"itemIndex":6,"x":-172.5,"y":3.87544417,"z":0.0,"rx":0.0,"ry":338.0,"rz":0.0},{"itemIndex":6,"x":-169.5,"y":3.795563,"z":0.0,"rx":0.0,"ry":75.0,"rz":0.0},{"itemIndex":6,"x":-166.5,"y":3.48349619,"z":0.0,"rx":0.0,"ry":227.0,"rz":0.0},{"itemIndex":6,"x":-163.5,"y":3.29740429,"z":0.0,"rx":0.0,"ry":159.0,"rz":0.0},{"itemIndex":6,"x":-156.0,"y":4.71710157,"z":0.0,"rx":0.0,"ry":187.0,"rz":0.0},{"itemIndex":6,"x":-147.0,"y":7.109715,"z":0.0,"rx":0.0,"ry":329.0,"rz":0.0},{"itemIndex":6,"x":-141.0,"y":9.304459,"z":0.0,"rx":0.0,"ry":251.0,"rz":0.0},{"itemIndex":6,"x":-139.5,"y":9.843694,"z":0.0,"rx":0.0,"ry":302.0,"rz":0.0},{"itemIndex":6,"x":-130.5,"y":10.905529,"z":0.0,"rx":0.0,"ry":49.0000038,"rz":0.0},{"itemIndex":6,"x":-127.5,"y":10.8514357,"z":0.0,"rx":0.0,"ry":136.0,"rz":0.0},{"itemIndex":6,"x":-120.0,"y":11.1766043,"z":0.0,"rx":0.0,"ry":353.0,"rz":0.0},{"itemIndex":0,"x":-114.0,"y":11.2043,"z":0.0,"rx":0.0,"ry":0.0,"rz":0.0},{"itemIndex":6,"x":-109.5,"y":10.6322746,"z":0.0,"rx":0.0,"ry":123.999992,"rz":0.0},{"itemIndex":6,"x":-108.0,"y":10.5992031,"z":0.0,"rx":0.0,"ry":342.0,"rz":0.0},{"itemIndex":6,"x":-105.0,"y":10.2303219,"z":0.0,"rx":0.0,"ry":2.0,"rz":0.0},{"itemIndex":6,"x":-169.5,"y":3.75070429,"z":-1.5,"rx":0.0,"ry":266.0,"rz":0.0},{"itemIndex":6,"x":-165.0,"y":3.25377536,"z":-1.5,"rx":0.0,"ry":356.0,"rz":0.0},{"itemIndex":6,"x":-163.5,"y":3.24173522,"z":-1.5,"rx":0.0,"ry":240.0,"rz":0.0},{"itemIndex":6,"x":-162.0,"y":3.4020083,"z":-1.5,"rx":0.0,"ry":186.0,"rz":0.0},{"itemIndex":6,"x":-157.5,"y":4.270366,"z":-1.5,"rx":0.0,"ry":182.0,"rz":0.0},{"itemIndex":6,"x":-151.5,"y":6.20879126,"z":-1.5,"rx":0.0,"ry":235.0,"rz":0.0},{"itemIndex":6,"x":-141.0,"y":9.322669,"z":-1.5,"rx":0.0,"ry":332.0,"rz":0.0},{"itemIndex":6,"x":-138.0,"y":10.3290243,"z":-1.5,"rx":0.0,"ry":333.0,"rz":0.0},{"itemIndex":6,"x":-136.5,"y":10.4440355,"z":-1.5,"rx":0.0,"ry":188.0,"rz":0.0},{"itemIndex":6,"x":-126.0,"y":11.5680113,"z":-1.5,"rx":0.0,"ry":133.0,"rz":0.0},{"itemIndex":6,"x":-111.0,"y":10.969121,"z":-1.5,"rx":0.0,"ry":5.0,"rz":0.0},{"itemIndex":6,"x":-106.5,"y":10.3400135,"z":-1.5,"rx":0.0,"ry":161.0,"rz":0.0},{"itemIndex":6,"x":-105.0,"y":10.2782087,"z":-1.5,"rx":0.0,"ry":143.0,"rz":0.0},{"itemIndex":6,"x":-166.5,"y":3.0923295,"z":-3.0,"rx":0.0,"ry":300.0,"rz":0.0},{"itemIndex":6,"x":-163.5,"y":3.22949171,"z":-3.0,"rx":0.0,"ry":357.0,"rz":0.0},{"itemIndex":6,"x":-159.0,"y":4.10811853,"z":-3.0,"rx":0.0,"ry":300.0,"rz":0.0},{"itemIndex":6,"x":-148.5,"y":7.43355274,"z":-3.0,"rx":0.0,"ry":191.0,"rz":0.0},{"itemIndex":6,"x":-147.0,"y":7.95930338,"z":-3.0,"rx":0.0,"ry":279.0,"rz":0.0},{"itemIndex":6,"x":-136.5,"y":10.2909327,"z":-3.0,"rx":0.0,"ry":257.0,"rz":0.0},{"itemIndex":6,"x":-133.5,"y":11.1590471,"z":-3.0,"rx":0.0,"ry":256.0,"rz":0.0},{"itemIndex":6,"x":-123.0,"y":12.5206108,"z":-3.0,"rx":0.0,"ry":249.0,"rz":0.0},{"itemIndex":6,"x":-111.0,"y":11.3624086,"z":-3.0,"rx":0.0,"ry":307.0,"rz":0.0},{"itemIndex":6,"x":-172.5,"y":3.57484818,"z":-4.5,"rx":0.0,"ry":94.99999,"rz":0.0},{"itemIndex":6,"x":-171.0,"y":3.47050142,"z":-4.5,"rx":0.0,"ry":353.0,"rz":0.0},{"itemIndex":6,"x":-166.5,"y":2.84144545,"z":-4.5,"rx":0.0,"ry":260.0,"rz":0.0},{"itemIndex":6,"x":-165.0,"y":3.01733756,"z":-4.5,"rx":0.0,"ry":237.0,"rz":0.0},{"itemIndex":6,"x":-160.5,"y":3.7447052,"z":-4.5,"rx":0.0,"ry":310.0,"rz":0.0},{"itemIndex":6,"x":-157.5,"y":4.41763735,"z":-4.5,"rx":0.0,"ry":174.0,"rz":0.0},{"itemIndex":6,"x":-154.5,"y":5.488641,"z":-4.5,"rx":0.0,"ry":258.0,"rz":0.0},{"itemIndex":6,"x":-142.5,"y":9.244138,"z":-4.5,"rx":0.0,"ry":25.0,"rz":0.0},{"itemIndex":6,"x":-138.0,"y":10.3037987,"z":-4.5,"rx":0.0,"ry":184.0,"rz":0.0},{"itemIndex":6,"x":-133.5,"y":11.1370106,"z":-4.5,"rx":0.0,"ry":148.0,"rz":0.0},{"itemIndex":6,"x":-129.0,"y":12.4546185,"z":-4.5,"rx":0.0,"ry":304.0,"rz":0.0},{"itemIndex":6,"x":-124.5,"y":12.8012428,"z":-4.5,"rx":0.0,"ry":108.0,"rz":0.0},{"itemIndex":6,"x":-118.5,"y":12.8107548,"z":-4.5,"rx":0.0,"ry":42.0,"rz":0.0},{"itemIndex":6,"x":-112.5,"y":12.1999445,"z":-4.5,"rx":0.0,"ry":311.0,"rz":0.0},{"itemIndex":6,"x":-111.0,"y":11.9337511,"z":-4.5,"rx":0.0,"ry":167.0,"rz":0.0},{"itemIndex":6,"x":-109.5,"y":11.7597075,"z":-4.5,"rx":0.0,"ry":222.0,"rz":0.0},{"itemIndex":6,"x":-172.5,"y":3.368254,"z":-6.0,"rx":0.0,"ry":177.0,"rz":0.0},{"itemIndex":6,"x":-171.0,"y":3.17491746,"z":-6.0,"rx":0.0,"ry":164.0,"rz":0.0},{"itemIndex":6,"x":-162.0,"y":3.1669147,"z":-6.0,"rx":0.0,"ry":245.0,"rz":0.0},{"itemIndex":6,"x":-153.0,"y":6.2903204,"z":-6.0,"rx":0.0,"ry":271.0,"rz":0.0},{"itemIndex":6,"x":-144.0,"y":8.734241,"z":-6.0,"rx":0.0,"ry":310.0,"rz":0.0},{"itemIndex":6,"x":-139.5,"y":9.873429,"z":-6.0,"rx":0.0,"ry":357.0,"rz":0.0},{"itemIndex":6,"x":-138.0,"y":10.3425789,"z":-6.0,"rx":0.0,"ry":68.0,"rz":0.0},{"itemIndex":6,"x":-126.0,"y":13.1207609,"z":-6.0,"rx":0.0,"ry":357.0,"rz":0.0},{"itemIndex":6,"x":-117.0,"y":13.1543865,"z":-6.0,"rx":0.0,"ry":59.0,"rz":0.0},{"itemIndex":6,"x":-114.0,"y":12.9342594,"z":-6.0,"rx":0.0,"ry":133.0,"rz":0.0},{"itemIndex":6,"x":-171.0,"y":2.9928,"z":-7.5,"rx":0.0,"ry":17.0,"rz":0.0},{"itemIndex":6,"x":-169.5,"y":2.72590065,"z":-7.5,"rx":0.0,"ry":29.0,"rz":0.0},{"itemIndex":6,"x":-163.5,"y":2.672248,"z":-7.5,"rx":0.0,"ry":52.0,"rz":0.0},{"itemIndex":6,"x":-154.5,"y":5.56888151,"z":-7.5,"rx":0.0,"ry":25.9999981,"rz":0.0},{"itemIndex":6,"x":-151.5,"y":6.650505,"z":-7.5,"rx":0.0,"ry":24.0,"rz":0.0},{"itemIndex":6,"x":-150.0,"y":6.73381948,"z":-7.5,"rx":0.0,"ry":238.0,"rz":0.0},{"itemIndex":6,"x":-144.0,"y":8.542429,"z":-7.5,"rx":0.0,"ry":287.0,"rz":0.0},{"itemIndex":6,"x":-133.5,"y":11.1132517,"z":-7.5,"rx":0.0,"ry":230.0,"rz":0.0},{"itemIndex":6,"x":-123.0,"y":13.7323074,"z":-7.5,"rx":0.0,"ry":185.0,"rz":0.0},{"itemIndex":6,"x":-114.0,"y":13.2258539,"z":-7.5,"rx":0.0,"ry":332.0,"rz":0.0},{"itemIndex":6,"x":-112.5,"y":12.9691811,"z":-7.5,"rx":0.0,"ry":250.0,"rz":0.0},{"itemIndex":6,"x":-171.0,"y":2.78224778,"z":-9.000004,"rx":0.0,"ry":227.0,"rz":0.0},{"itemIndex":6,"x":-168.0,"y":2.32604742,"z":-9.000004,"rx":0.0,"ry":41.0,"rz":0.0},{"itemIndex":6,"x":-166.5,"y":2.22049713,"z":-9.000004,"rx":0.0,"ry":70.0,"rz":0.0},{"itemIndex":6,"x":-157.5,"y":4.27441359,"z":-9.000004,"rx":0.0,"ry":286.0,"rz":0.0},{"itemIndex":6,"x":-151.5,"y":6.329553,"z":-9.000004,"rx":0.0,"ry":123.0,"rz":0.0},{"itemIndex":6,"x":-147.0,"y":7.33246851,"z":-9.000004,"rx":0.0,"ry":268.0,"rz":0.0},{"itemIndex":6,"x":-142.5,"y":8.679075,"z":-9.000004,"rx":0.0,"ry":277.0,"rz":0.0},{"itemIndex":6,"x":-138.0,"y":10.3701582,"z":-9.000004,"rx":0.0,"ry":5.0,"rz":0.0},{"itemIndex":0,"x":-136.5,"y":10.5392609,"z":-9.000004,"rx":0.0,"ry":0.0,"rz":0.0},{"itemIndex":6,"x":-133.5,"y":11.16162,"z":-9.000004,"rx":0.0,"ry":194.0,"rz":0.0},{"itemIndex":6,"x":-126.0,"y":13.7220535,"z":-9.000004,"rx":0.0,"ry":244.0,"rz":0.0},{"itemIndex":6,"x":-124.5,"y":13.8447933,"z":-9.000004,"rx":0.0,"ry":23.0,"rz":0.0},{"itemIndex":6,"x":-121.5,"y":13.9920034,"z":-9.000004,"rx":0.0,"ry":324.0,"rz":0.0},{"itemIndex":6,"x":-115.5,"y":13.5895786,"z":-9.000004,"rx":0.0,"ry":296.0,"rz":0.0},{"itemIndex":6,"x":-108.0,"y":12.9494486,"z":-9.000004,"rx":0.0,"ry":102.0,"rz":0.0},{"itemIndex":6,"x":-168.0,"y":2.23926,"z":-10.5,"rx":0.0,"ry":185.0,"rz":0.0},{"itemIndex":6,"x":-159.0,"y":3.96940875,"z":-10.5,"rx":0.0,"ry":337.0,"rz":0.0},{"itemIndex":6,"x":-157.5,"y":4.29743528,"z":-10.5,"rx":0.0,"ry":212.0,"rz":0.0},{"itemIndex":6,"x":-156.0,"y":5.05111933,"z":-10.5,"rx":0.0,"ry":37.0,"rz":0.0},{"itemIndex":6,"x":-145.5,"y":7.79062748,"z":-10.5,"rx":0.0,"ry":185.0,"rz":0.0},{"itemIndex":6,"x":-130.5,"y":12.057065,"z":-10.5,"rx":0.0,"ry":123.999992,"rz":0.0},{"itemIndex":6,"x":-129.0,"y":12.6687479,"z":-10.5,"rx":0.0,"ry":88.0,"rz":0.0},{"itemIndex":6,"x":-127.5,"y":13.0718889,"z":-10.5,"rx":0.0,"ry":155.0,"rz":0.0},{"itemIndex":6,"x":-126.0,"y":13.5803118,"z":-10.5,"rx":0.0,"ry":158.0,"rz":0.0},{"itemIndex":6,"x":-124.5,"y":13.8974257,"z":-10.5,"rx":0.0,"ry":233.0,"rz":0.0},{"itemIndex":6,"x":-123.0,"y":14.3246918,"z":-10.5,"rx":0.0,"ry":171.0,"rz":0.0},{"itemIndex":0,"x":-123.0,"y":14.3246918,"z":-10.5,"rx":0.0,"ry":0.0,"rz":0.0},{"itemIndex":6,"x":-118.5,"y":13.9299641,"z":-10.5,"rx":0.0,"ry":325.0,"rz":0.0},{"itemIndex":6,"x":-117.0,"y":13.6945562,"z":-10.5,"rx":0.0,"ry":213.0,"rz":0.0},{"itemIndex":6,"x":-114.0,"y":13.5896931,"z":-10.5,"rx":0.0,"ry":309.0,"rz":0.0},{"itemIndex":6,"x":-112.5,"y":13.3853,"z":-10.5,"rx":0.0,"ry":201.0,"rz":0.0},{"itemIndex":6,"x":-106.5,"y":13.0912943,"z":-10.5,"rx":0.0,"ry":333.0,"rz":0.0},{"itemIndex":6,"x":-105.0,"y":13.1434412,"z":-10.5,"rx":0.0,"ry":34.0,"rz":0.0},{"itemIndex":6,"x":-172.5,"y":2.440399,"z":-12.0,"rx":0.0,"ry":326.0,"rz":0.0},{"itemIndex":6,"x":-162.0,"y":3.27393222,"z":-12.0,"rx":0.0,"ry":311.0,"rz":0.0},{"itemIndex":6,"x":-160.5,"y":3.45498443,"z":-12.0,"rx":0.0,"ry":301.0,"rz":0.0},{"itemIndex":6,"x":-159.0,"y":3.90161657,"z":-12.0,"rx":0.0,"ry":155.0,"rz":0.0},{"itemIndex":6,"x":-150.0,"y":6.7223115,"z":-12.0,"rx":0.0,"ry":292.0,"rz":0.0},{"itemIndex":6,"x":-145.5,"y":7.94457436,"z":-12.0,"rx":0.0,"ry":300.0,"rz":0.0},{"itemIndex":6,"x":-144.0,"y":8.45945,"z":-12.0,"rx":0.0,"ry":77.0,"rz":0.0},{"itemIndex":6,"x":-138.0,"y":10.7070656,"z":-12.0,"rx":0.0,"ry":345.0,"rz":0.0},{"itemIndex":6,"x":-136.5,"y":10.9663782,"z":-12.0,"rx":0.0,"ry":209.0,"rz":0.0},{"itemIndex":6,"x":-133.5,"y":11.6531849,"z":-12.0,"rx":0.0,"ry":155.0,"rz":0.0},{"itemIndex":6,"x":-130.5,"y":12.3185635,"z":-12.0,"rx":0.0,"ry":322.0,"rz":0.0},{"itemIndex":6,"x":-127.5,"y":12.9940195,"z":-12.0,"rx":0.0,"ry":335.0,"rz":0.0},{"itemIndex":6,"x":-124.5,"y":13.6790371,"z":-12.0,"rx":0.0,"ry":172.0,"rz":0.0},{"itemIndex":6,"x":-123.0,"y":14.0613737,"z":-12.0,"rx":0.0,"ry":108.0,"rz":0.0},{"itemIndex":6,"x":-120.0,"y":14.2550545,"z":-12.0,"rx":0.0,"ry":225.0,"rz":0.0},{"itemIndex":6,"x":-118.5,"y":14.2016935,"z":-12.0,"rx":0.0,"ry":306.0,"rz":0.0},{"itemIndex":6,"x":-117.0,"y":14.0331526,"z":-12.0,"rx":0.0,"ry":276.0,"rz":0.0},{"itemIndex":6,"x":-115.5,"y":13.8285561,"z":-12.0,"rx":0.0,"ry":340.0,"rz":0.0},{"itemIndex":6,"x":-112.5,"y":13.79035,"z":-12.0,"rx":0.0,"ry":149.0,"rz":0.0},{"itemIndex":6,"x":-109.5,"y":13.9913912,"z":-12.0,"rx":0.0,"ry":97.0,"rz":0.0},{"itemIndex":6,"x":-106.5,"y":13.6583691,"z":-12.0,"rx":0.0,"ry":195.0,"rz":0.0},{"itemIndex":6,"x":-105.0,"y":13.4427538,"z":-12.0,"rx":0.0,"ry":262.0,"rz":0.0},{"itemIndex":0,"x":-171.0,"y":2.24153137,"z":-13.5,"rx":0.0,"ry":0.0,"rz":0.0},{"itemIndex":6,"x":-151.5,"y":6.40426636,"z":-13.5,"rx":0.0,"ry":306.0,"rz":0.0},{"itemIndex":6,"x":-147.0,"y":7.450256,"z":-13.5,"rx":0.0,"ry":37.0,"rz":0.0},{"itemIndex":6,"x":-145.5,"y":7.91546631,"z":-13.5,"rx":0.0,"ry":202.0,"rz":0.0},{"itemIndex":6,"x":-141.0,"y":9.702927,"z":-13.5,"rx":0.0,"ry":219.0,"rz":0.0},{"itemIndex":6,"x":-135.0,"y":11.5287285,"z":-13.5,"rx":0.0,"ry":9.000001,"rz":0.0},{"itemIndex":6,"x":-124.5,"y":13.7572374,"z":-13.5,"rx":0.0,"ry":116.999992,"rz":0.0},{"itemIndex":6,"x":-121.5,"y":14.495821,"z":-13.5,"rx":0.0,"ry":358.0,"rz":0.0},{"itemIndex":6,"x":-117.0,"y":14.46963,"z":-13.5,"rx":0.0,"ry":220.0,"rz":0.0},{"itemIndex":6,"x":-114.0,"y":14.1058626,"z":-13.5,"rx":0.0,"ry":102.0,"rz":0.0},{"itemIndex":6,"x":-108.0,"y":14.2674646,"z":-13.5,"rx":0.0,"ry":303.0,"rz":0.0},{"itemIndex":6,"x":-106.5,"y":14.2352562,"z":-13.5,"rx":0.0,"ry":99.0,"rz":0.0},{"itemIndex":6,"x":-168.0,"y":2.45080876,"z":-15.0,"rx":0.0,"ry":218.0,"rz":0.0},{"itemIndex":6,"x":-160.5,"y":3.37429667,"z":-15.0,"rx":0.0,"ry":248.0,"rz":0.0},{"itemIndex":6,"x":-159.0,"y":3.97790623,"z":-15.0,"rx":0.0,"ry":135.0,"rz":0.0},{"itemIndex":6,"x":-147.0,"y":7.50801373,"z":-15.0,"rx":0.0,"ry":223.0,"rz":0.0},{"itemIndex":6,"x":-145.5,"y":7.88143253,"z":-15.0,"rx":0.0,"ry":339.0,"rz":0.0},{"itemIndex":6,"x":-127.5,"y":13.6719837,"z":-15.0,"rx":0.0,"ry":143.0,"rz":0.0},{"itemIndex":6,"x":-124.5,"y":14.0780849,"z":-15.0,"rx":0.0,"ry":180.0,"rz":0.0},{"itemIndex":6,"x":-118.5,"y":14.7284527,"z":-15.0,"rx":0.0,"ry":277.0,"rz":0.0},{"itemIndex":6,"x":-114.0,"y":14.763938,"z":-15.0,"rx":0.0,"ry":9.000001,"rz":0.0},{"itemIndex":6,"x":-108.0,"y":14.8496361,"z":-15.0,"rx":0.0,"ry":7.999999,"rz":0.0},{"itemIndex":6,"x":-168.0,"y":2.83188772,"z":-16.5,"rx":0.0,"ry":9.000001,"rz":0.0},{"itemIndex":6,"x":-162.0,"y":3.20328927,"z":-16.5,"rx":0.0,"ry":152.0,"rz":0.0},{"itemIndex":6,"x":-159.0,"y":3.98839664,"z":-16.5,"rx":0.0,"ry":164.0,"rz":0.0},{"itemIndex":6,"x":-154.5,"y":5.65264,"z":-16.5,"rx":0.0,"ry":97.0,"rz":0.0},{"itemIndex":6,"x":-153.0,"y":6.067046,"z":-16.5,"rx":0.0,"ry":349.0,"rz":0.0},{"itemIndex":6,"x":-151.5,"y":6.37240744,"z":-16.5,"rx":0.0,"ry":265.0,"rz":0.0},{"itemIndex":6,"x":-148.5,"y":7.147568,"z":-16.5,"rx":0.0,"ry":239.0,"rz":0.0},{"itemIndex":6,"x":-142.5,"y":9.588945,"z":-16.5,"rx":0.0,"ry":131.0,"rz":0.0},{"itemIndex":6,"x":-138.0,"y":10.6440372,"z":-16.5,"rx":0.0,"ry":224.0,"rz":0.0},{"itemIndex":6,"x":-106.5,"y":15.2020607,"z":-16.5,"rx":0.0,"ry":280.0,"rz":0.0},{"itemIndex":0,"x":-166.5,"y":3.431015,"z":-18.0,"rx":0.0,"ry":0.0,"rz":0.0},{"itemIndex":6,"x":-162.0,"y":3.550963,"z":-18.0,"rx":0.0,"ry":207.0,"rz":0.0},{"itemIndex":6,"x":-160.5,"y":3.648079,"z":-18.0,"rx":0.0,"ry":210.0,"rz":0.0},{"itemIndex":6,"x":-147.0,"y":8.109246,"z":-18.0,"rx":0.0,"ry":122.000008,"rz":0.0},{"itemIndex":6,"x":-145.5,"y":8.811918,"z":-18.0,"rx":0.0,"ry":109.0,"rz":0.0},{"itemIndex":6,"x":-138.0,"y":10.9914179,"z":-18.0,"rx":0.0,"ry":331.0,"rz":0.0},{"itemIndex":6,"x":-136.5,"y":11.3463545,"z":-18.0,"rx":0.0,"ry":56.0000038,"rz":0.0},{"itemIndex":6,"x":-133.5,"y":12.4022217,"z":-18.0,"rx":0.0,"ry":103.0,"rz":0.0},{"itemIndex":6,"x":-132.0,"y":13.3283262,"z":-18.0,"rx":0.0,"ry":306.0,"rz":0.0},{"itemIndex":6,"x":-129.0,"y":13.8802919,"z":-18.0,"rx":0.0,"ry":220.0,"rz":0.0},{"itemIndex":6,"x":-126.0,"y":14.2629175,"z":-18.0,"rx":0.0,"ry":276.0,"rz":0.0},{"itemIndex":6,"x":-115.5,"y":15.3673573,"z":-18.0,"rx":0.0,"ry":343.0,"rz":0.0},{"itemIndex":6,"x":-111.0,"y":15.61841,"z":-18.0,"rx":0.0,"ry":239.0,"rz":0.0},{"itemIndex":6,"x":-109.5,"y":15.5357094,"z":-18.0,"rx":0.0,"ry":182.0,"rz":0.0},{"itemIndex":0,"x":-106.5,"y":15.4177856,"z":-18.0,"rx":0.0,"ry":0.0,"rz":0.0},{"itemIndex":6,"x":-105.0,"y":15.5015965,"z":-18.0,"rx":0.0,"ry":273.0,"rz":0.0},{"itemIndex":6,"x":-168.0,"y":3.4656055,"z":-19.5,"rx":0.0,"ry":165.0,"rz":0.0},{"itemIndex":6,"x":-165.0,"y":3.87416887,"z":-19.5,"rx":0.0,"ry":92.0,"rz":0.0},{"itemIndex":6,"x":-162.0,"y":3.94133329,"z":-19.5,"rx":0.0,"ry":108.0,"rz":0.0},{"itemIndex":6,"x":-160.5,"y":3.93772316,"z":-19.5,"rx":0.0,"ry":85.0,"rz":0.0},{"itemIndex":6,"x":-147.0,"y":8.19083,"z":-19.5,"rx":0.0,"ry":86.99999,"rz":0.0},{"itemIndex":6,"x":-145.5,"y":9.022387,"z":-19.5,"rx":0.0,"ry":189.0,"rz":0.0},{"itemIndex":6,"x":-141.0,"y":10.4177017,"z":-19.5,"rx":0.0,"ry":82.0,"rz":0.0},{"itemIndex":6,"x":-135.0,"y":12.0529842,"z":-19.5,"rx":0.0,"ry":315.0,"rz":0.0},{"itemIndex":6,"x":-124.5,"y":14.9044333,"z":-19.5,"rx":0.0,"ry":97.0,"rz":0.0},{"itemIndex":6,"x":-121.5,"y":15.5343008,"z":-19.5,"rx":0.0,"ry":162.0,"rz":0.0},{"itemIndex":6,"x":-120.0,"y":15.83493,"z":-19.5,"rx":0.0,"ry":45.0000038,"rz":0.0},{"itemIndex":6,"x":-118.5,"y":15.9760838,"z":-19.5,"rx":0.0,"ry":168.0,"rz":0.0},{"itemIndex":6,"x":-111.0,"y":15.8305759,"z":-19.5,"rx":0.0,"ry":334.0,"rz":0.0},{"itemIndex":6,"x":-108.0,"y":15.83087,"z":-19.5,"rx":0.0,"ry":71.99999,"rz":0.0},{"itemIndex":6,"x":-171.0,"y":3.37850428,"z":-21.0,"rx":0.0,"ry":155.0,"rz":0.0},{"itemIndex":6,"x":-168.0,"y":3.66563,"z":-21.0,"rx":0.0,"ry":342.0,"rz":0.0},{"itemIndex":6,"x":-160.5,"y":3.98444724,"z":-21.0,"rx":0.0,"ry":199.0,"rz":0.0},{"itemIndex":6,"x":-151.5,"y":6.54384041,"z":-21.0,"rx":0.0,"ry":32.0,"rz":0.0},{"itemIndex":6,"x":-150.0,"y":6.79843855,"z":-21.0,"rx":0.0,"ry":270.0,"rz":0.0},{"itemIndex":6,"x":-148.5,"y":7.2187686,"z":-21.0,"rx":0.0,"ry":237.0,"rz":0.0},{"itemIndex":6,"x":-144.0,"y":9.305724,"z":-21.0,"rx":0.0,"ry":2.0,"rz":0.0},{"itemIndex":6,"x":-130.5,"y":13.7045078,"z":-21.0,"rx":0.0,"ry":212.0,"rz":0.0},{"itemIndex":6,"x":-129.0,"y":13.85921,"z":-21.0,"rx":0.0,"ry":141.0,"rz":0.0},{"itemIndex":6,"x":-127.5,"y":14.2212181,"z":-21.0,"rx":0.0,"ry":335.0,"rz":0.0},{"itemIndex":6,"x":-126.0,"y":14.5996342,"z":-21.0,"rx":0.0,"ry":354.0,"rz":0.0},{"itemIndex":6,"x":-124.5,"y":15.06052,"z":-21.0,"rx":0.0,"ry":254.0,"rz":0.0},{"itemIndex":6,"x":-123.0,"y":15.2750721,"z":-21.0,"rx":0.0,"ry":285.0,"rz":0.0},{"itemIndex":6,"x":-121.5,"y":15.8302765,"z":-21.0,"rx":0.0,"ry":129.0,"rz":0.0},{"itemIndex":6,"x":-120.0,"y":16.3041573,"z":-21.0,"rx":0.0,"ry":327.0,"rz":0.0},{"itemIndex":6,"x":-118.5,"y":16.5750561,"z":-21.0,"rx":0.0,"ry":127.000008,"rz":0.0},{"itemIndex":6,"x":-117.0,"y":16.7467327,"z":-21.0,"rx":0.0,"ry":137.0,"rz":0.0},{"itemIndex":6,"x":-105.0,"y":15.6338053,"z":-21.0,"rx":0.0,"ry":30.0000019,"rz":0.0},{"itemIndex":6,"x":-159.0,"y":4.4652667,"z":-22.5,"rx":0.0,"ry":234.0,"rz":0.0},{"itemIndex":6,"x":-156.0,"y":5.56318045,"z":-22.5,"rx":0.0,"ry":203.0,"rz":0.0},{"itemIndex":6,"x":-148.5,"y":7.20718241,"z":-22.5,"rx":0.0,"ry":292.0,"rz":0.0},{"itemIndex":6,"x":-141.0,"y":10.2102089,"z":-22.5,"rx":0.0,"ry":321.0,"rz":0.0},{"itemIndex":6,"x":-138.0,"y":11.4950237,"z":-22.5,"rx":0.0,"ry":232.0,"rz":0.0},{"itemIndex":6,"x":-136.5,"y":11.66581,"z":-22.5,"rx":0.0,"ry":45.0000038,"rz":0.0},{"itemIndex":6,"x":-132.0,"y":13.2706957,"z":-22.5,"rx":0.0,"ry":142.0,"rz":0.0},{"itemIndex":6,"x":-127.5,"y":14.1689005,"z":-22.5,"rx":0.0,"ry":223.0,"rz":0.0},{"itemIndex":6,"x":-126.0,"y":14.6187716,"z":-22.5,"rx":0.0,"ry":123.0,"rz":0.0},{"itemIndex":6,"x":-112.5,"y":16.8032875,"z":-22.5,"rx":0.0,"ry":338.0,"rz":0.0},{"itemIndex":6,"x":-172.5,"y":3.91864133,"z":-24.0,"rx":0.0,"ry":344.0,"rz":0.0},{"itemIndex":6,"x":-169.5,"y":4.08139372,"z":-24.0,"rx":0.0,"ry":92.0,"rz":0.0},{"itemIndex":6,"x":-162.0,"y":4.532283,"z":-24.0,"rx":0.0,"ry":232.0,"rz":0.0},{"itemIndex":6,"x":-160.5,"y":4.67279625,"z":-24.0,"rx":0.0,"ry":142.0,"rz":0.0},{"itemIndex":6,"x":-153.0,"y":6.322988,"z":-24.0,"rx":0.0,"ry":76.0,"rz":0.0},{"itemIndex":6,"x":-151.5,"y":6.618533,"z":-24.0,"rx":0.0,"ry":136.0,"rz":0.0},{"itemIndex":6,"x":-142.5,"y":9.67616,"z":-24.0,"rx":0.0,"ry":248.0,"rz":0.0},{"itemIndex":6,"x":-136.5,"y":11.8471575,"z":-24.0,"rx":0.0,"ry":157.0,"rz":0.0},{"itemIndex":6,"x":-135.0,"y":12.0315323,"z":-24.0,"rx":0.0,"ry":17.0,"rz":0.0},{"itemIndex":6,"x":-129.0,"y":13.7533426,"z":-24.0,"rx":0.0,"ry":218.0,"rz":0.0},{"itemIndex":0,"x":-123.0,"y":15.6703949,"z":-24.0,"rx":0.0,"ry":0.0,"rz":0.0},{"itemIndex":6,"x":-115.5,"y":18.0279388,"z":-24.0,"rx":0.0,"ry":276.0,"rz":0.0},{"itemIndex":6,"x":-109.5,"y":16.5786057,"z":-24.0,"rx":0.0,"ry":223.0,"rz":0.0},{"itemIndex":6,"x":-106.5,"y":16.1901722,"z":-24.0,"rx":0.0,"ry":251.0,"rz":0.0},{"itemIndex":6,"x":-168.0,"y":4.73417425,"z":-25.4999962,"rx":0.0,"ry":340.0,"rz":0.0},{"itemIndex":6,"x":-166.5,"y":4.72289848,"z":-25.4999962,"rx":0.0,"ry":233.0,"rz":0.0},{"itemIndex":6,"x":-160.5,"y":5.356529,"z":-25.4999962,"rx":0.0,"ry":290.0,"rz":0.0},{"itemIndex":6,"x":-130.5,"y":13.1224508,"z":-25.4999962,"rx":0.0,"ry":255.0,"rz":0.0},{"itemIndex":0,"x":-130.5,"y":13.1224518,"z":-25.4999962,"rx":0.0,"ry":0.0,"rz":0.0},{"itemIndex":6,"x":-129.0,"y":13.6251678,"z":-25.4999962,"rx":0.0,"ry":153.0,"rz":0.0},{"itemIndex":6,"x":-127.5,"y":13.942,"z":-25.4999962,"rx":0.0,"ry":155.0,"rz":0.0},{"itemIndex":6,"x":-124.5,"y":15.4086332,"z":-25.4999962,"rx":0.0,"ry":170.0,"rz":0.0},{"itemIndex":6,"x":-123.0,"y":16.0413952,"z":-25.4999962,"rx":0.0,"ry":123.0,"rz":0.0},{"itemIndex":6,"x":-114.0,"y":18.07453,"z":-25.4999962,"rx":0.0,"ry":219.0,"rz":0.0},{"itemIndex":6,"x":-109.5,"y":16.8242149,"z":-25.4999962,"rx":0.0,"ry":75.0,"rz":0.0},{"itemIndex":0,"x":-108.0,"y":16.386795,"z":-25.4999962,"rx":0.0,"ry":0.0,"rz":0.0},{"itemIndex":6,"x":-105.0,"y":16.26603,"z":-25.4999962,"rx":0.0,"ry":66.0,"rz":0.0},{"itemIndex":6,"x":-169.5,"y":5.21710253,"z":-27.0,"rx":0.0,"ry":11.0,"rz":0.0},{"itemIndex":6,"x":-157.5,"y":6.18904448,"z":-27.0,"rx":0.0,"ry":266.0,"rz":0.0},{"itemIndex":6,"x":-153.0,"y":6.978158,"z":-27.0,"rx":0.0,"ry":212.0,"rz":0.0},{"itemIndex":6,"x":-144.0,"y":9.517411,"z":-27.0,"rx":0.0,"ry":324.0,"rz":0.0},{"itemIndex":6,"x":-138.0,"y":11.2880974,"z":-27.0,"rx":0.0,"ry":310.0,"rz":0.0},{"itemIndex":6,"x":-133.5,"y":12.14315,"z":-27.0,"rx":0.0,"ry":81.0,"rz":0.0},{"itemIndex":6,"x":-129.0,"y":13.5773048,"z":-27.0,"rx":0.0,"ry":319.0,"rz":0.0},{"itemIndex":6,"x":-126.0,"y":14.7007847,"z":-27.0,"rx":0.0,"ry":25.0,"rz":0.0},{"itemIndex":6,"x":-109.5,"y":16.7527523,"z":-27.0,"rx":0.0,"ry":2.0,"rz":0.0},{"itemIndex":6,"x":-108.0,"y":16.5138454,"z":-27.0,"rx":0.0,"ry":163.0,"rz":0.0},{"itemIndex":6,"x":-166.5,"y":5.64789,"z":-28.5,"rx":0.0,"ry":183.0,"rz":0.0},{"itemIndex":6,"x":-160.5,"y":6.17990828,"z":-28.5,"rx":0.0,"ry":125.0,"rz":0.0},{"itemIndex":0,"x":-159.0,"y":6.447632,"z":-28.5,"rx":0.0,"ry":0.0,"rz":0.0},{"itemIndex":6,"x":-154.5,"y":6.90844059,"z":-28.5,"rx":0.0,"ry":119.0,"rz":0.0},{"itemIndex":6,"x":-148.5,"y":7.80416059,"z":-28.5,"rx":0.0,"ry":147.0,"rz":0.0},{"itemIndex":6,"x":-144.0,"y":9.664996,"z":-28.5,"rx":0.0,"ry":277.0,"rz":0.0},{"itemIndex":6,"x":-141.0,"y":10.7015219,"z":-28.5,"rx":0.0,"ry":28.0000019,"rz":0.0},{"itemIndex":6,"x":-138.0,"y":11.0680637,"z":-28.5,"rx":0.0,"ry":61.9999962,"rz":0.0},{"itemIndex":6,"x":-135.0,"y":11.4558,"z":-28.5,"rx":0.0,"ry":224.0,"rz":0.0},{"itemIndex":6,"x":-133.5,"y":11.9143782,"z":-28.5,"rx":0.0,"ry":91.00001,"rz":0.0},{"itemIndex":6,"x":-132.0,"y":12.6977692,"z":-28.5,"rx":0.0,"ry":304.0,"rz":0.0},{"itemIndex":6,"x":-129.0,"y":13.6981506,"z":-28.5,"rx":0.0,"ry":249.0,"rz":0.0},{"itemIndex":6,"x":-111.0,"y":17.22406,"z":-28.5,"rx":0.0,"ry":335.0,"rz":0.0},{"itemIndex":6,"x":-105.0,"y":16.5456982,"z":-28.5,"rx":0.0,"ry":114.0,"rz":0.0},{"itemIndex":6,"x":-169.5,"y":6.09199238,"z":-30.0,"rx":0.0,"ry":22.0,"rz":0.0},{"itemIndex":6,"x":-162.0,"y":6.0391264,"z":-30.0,"rx":0.0,"ry":321.0,"rz":0.0},{"itemIndex":6,"x":-160.5,"y":6.24411058,"z":-30.0,"rx":0.0,"ry":301.0,"rz":0.0},{"itemIndex":0,"x":-160.5,"y":6.24411,"z":-30.0,"rx":0.0,"ry":0.0,"rz":0.0},{"itemIndex":6,"x":-159.0,"y":6.457936,"z":-30.0,"rx":0.0,"ry":289.0,"rz":0.0},{"itemIndex":0,"x":-151.5,"y":7.421051,"z":-30.0,"rx":0.0,"ry":0.0,"rz":0.0},{"itemIndex":6,"x":-150.0,"y":7.840758,"z":-30.0,"rx":0.0,"ry":81.0,"rz":0.0},{"itemIndex":6,"x":-147.0,"y":8.60467,"z":-30.0,"rx":0.0,"ry":103.0,"rz":0.0},{"itemIndex":6,"x":-144.0,"y":10.0425377,"z":-30.0,"rx":0.0,"ry":123.999992,"rz":0.0},{"itemIndex":6,"x":-141.0,"y":11.0110092,"z":-30.0,"rx":0.0,"ry":32.0,"rz":0.0},{"itemIndex":6,"x":-139.5,"y":11.1658411,"z":-30.0,"rx":0.0,"ry":303.0,"rz":0.0},{"itemIndex":6,"x":-126.0,"y":14.9305372,"z":-30.0,"rx":0.0,"ry":99.0,"rz":0.0},{"itemIndex":6,"x":-124.5,"y":15.8130045,"z":-30.0,"rx":0.0,"ry":173.0,"rz":0.0},{"itemIndex":6,"x":-112.5,"y":17.8040447,"z":-30.0,"rx":0.0,"ry":258.0,"rz":0.0},{"itemIndex":6,"x":-105.0,"y":16.3161469,"z":-30.0,"rx":0.0,"ry":269.0,"rz":0.0},{"itemIndex":6,"x":-169.5,"y":6.12087965,"z":-31.5,"rx":0.0,"ry":306.0,"rz":0.0},{"itemIndex":6,"x":-166.5,"y":6.095223,"z":-31.5,"rx":0.0,"ry":165.0,"rz":0.0},{"itemIndex":6,"x":-165.0,"y":5.78302336,"z":-31.5,"rx":0.0,"ry":306.0,"rz":0.0},{"itemIndex":6,"x":-162.0,"y":5.963457,"z":-31.5,"rx":0.0,"ry":219.0,"rz":0.0},{"itemIndex":6,"x":-151.5,"y":7.32596636,"z":-31.5,"rx":0.0,"ry":334.0,"rz":0.0},{"itemIndex":6,"x":-150.0,"y":7.82362556,"z":-31.5,"rx":0.0,"ry":356.0,"rz":0.0},{"itemIndex":6,"x":-148.5,"y":8.326411,"z":-31.5,"rx":0.0,"ry":259.0,"rz":0.0},{"itemIndex":6,"x":-145.5,"y":9.607661,"z":-31.5,"rx":0.0,"ry":347.0,"rz":0.0},{"itemIndex":6,"x":-133.5,"y":12.1068945,"z":-31.5,"rx":0.0,"ry":48.0,"rz":0.0},{"itemIndex":6,"x":-121.5,"y":16.89575,"z":-31.5,"rx":0.0,"ry":63.0,"rz":0.0},{"itemIndex":6,"x":-118.5,"y":17.31358,"z":-31.5,"rx":0.0,"ry":330.0,"rz":0.0},{"itemIndex":0,"x":-111.0,"y":17.33313,"z":-31.5,"rx":0.0,"ry":0.0,"rz":0.0},{"itemIndex":6,"x":-109.5,"y":16.84412,"z":-31.5,"rx":0.0,"ry":122.000008,"rz":0.0},{"itemIndex":6,"x":-168.0,"y":6.04175138,"z":-33.0,"rx":0.0,"ry":165.0,"rz":0.0},{"itemIndex":6,"x":-163.5,"y":5.9903183,"z":-33.0,"rx":0.0,"ry":140.0,"rz":0.0},{"itemIndex":6,"x":-162.0,"y":6.05782461,"z":-33.0,"rx":0.0,"ry":248.0,"rz":0.0},{"itemIndex":6,"x":-160.5,"y":6.232478,"z":-33.0,"rx":0.0,"ry":245.0,"rz":0.0},{"itemIndex":6,"x":-159.0,"y":6.42682934,"z":-33.0,"rx":0.0,"ry":177.0,"rz":0.0},{"itemIndex":6,"x":-156.0,"y":7.129314,"z":-33.0,"rx":0.0,"ry":39.0,"rz":0.0},{"itemIndex":6,"x":-153.0,"y":7.273805,"z":-33.0,"rx":0.0,"ry":112.0,"rz":0.0},{"itemIndex":6,"x":-151.5,"y":7.511896,"z":-33.0,"rx":0.0,"ry":105.0,"rz":0.0},{"itemIndex":6,"x":-148.5,"y":8.767085,"z":-33.0,"rx":0.0,"ry":169.0,"rz":0.0},{"itemIndex":6,"x":-142.5,"y":10.8465014,"z":-33.0,"rx":0.0,"ry":178.0,"rz":0.0},{"itemIndex":6,"x":-138.0,"y":11.7885065,"z":-33.0,"rx":0.0,"ry":14.000001,"rz":0.0},{"itemIndex":6,"x":-133.5,"y":12.2418556,"z":-33.0,"rx":0.0,"ry":183.0,"rz":0.0},{"itemIndex":6,"x":-130.5,"y":12.759119,"z":-33.0,"rx":0.0,"ry":261.0,"rz":0.0},{"itemIndex":6,"x":-129.0,"y":13.3405046,"z":-33.0,"rx":0.0,"ry":76.0,"rz":0.0},{"itemIndex":6,"x":-124.5,"y":14.7402172,"z":-33.0,"rx":0.0,"ry":128.0,"rz":0.0},{"itemIndex":6,"x":-123.0,"y":15.5983934,"z":-33.0,"rx":0.0,"ry":140.0,"rz":0.0},{"itemIndex":6,"x":-121.5,"y":16.464365,"z":-33.0,"rx":0.0,"ry":266.0,"rz":0.0},{"itemIndex":6,"x":-118.5,"y":17.37241,"z":-33.0,"rx":0.0,"ry":309.0,"rz":0.0},{"itemIndex":6,"x":-117.0,"y":17.5837021,"z":-33.0,"rx":0.0,"ry":21.0,"rz":0.0},{"itemIndex":6,"x":-112.5,"y":17.6504822,"z":-33.0,"rx":0.0,"ry":202.0,"rz":0.0},{"itemIndex":6,"x":-109.5,"y":16.6915722,"z":-33.0,"rx":0.0,"ry":225.0,"rz":0.0}]}